[
  {
    "id": "8150003",
    "dep": "08",
    "enseigne": "TotalEnergies Contact",
    "adresse": "89 AVENUE DES MARTYRS DE LA RESISTANCE",
    "cp": "08150",
    "ville": "RENWEZ",
    "latitude": 49.833628,
    "longitude": 4.603904,
    "carburants": {
      "Gazole": {
        "valeur": "1.930",
        "maj": "2026-07-07 09:52:00"
      },
      "SP95": {
        "valeur": "1.960",
        "maj": "2026-07-07 09:52:00"
      }
    }
  },
  {
    "id": "8090001",
    "dep": "08",
    "enseigne": "Esso Express",
    "adresse": "RN 43 LE PORT LEROY",
    "cp": "08090",
    "ville": "Cliron",
    "latitude": 49.805,
    "longitude": 4.621,
    "carburants": {
      "Gazole": {
        "valeur": "1.933",
        "maj": "2026-07-09 12:20:00"
      },
      "E10": {
        "valeur": "1.966",
        "maj": "2026-07-09 12:20:00"
      },
      "SP98": {
        "valeur": "2.064",
        "maj": "2026-07-09 12:20:00"
      }
    }
  },
  {
    "id": "8330002",
    "dep": "08",
    "enseigne": "Carrefour Contact",
    "adresse": "12 RUE PIERRE VIENOT",
    "cp": "08330",
    "ville": "VRIGNE-AUX-BOIS",
    "latitude": 49.735,
    "longitude": 4.85,
    "carburants": {
      "Gazole": {
        "valeur": "1.929",
        "maj": "2026-07-01 05:40:26"
      },
      "SP95": {
        "valeur": "1.989",
        "maj": "2026-07-01 05:40:27"
      },
      "SP98": {
        "valeur": "2.069",
        "maj": "2026-07-01 05:40:27"
      }
    }
  },
  {
    "id": "8130003",
    "dep": "08",
    "enseigne": "Carrefour Contact",
    "adresse": "3 Rue Saint-Charles",
    "cp": "08130",
    "ville": "Attigny",
    "latitude": 49.479,
    "longitude": 4.577,
    "carburants": {
      "Gazole": {
        "valeur": "1.910",
        "maj": "2026-07-06 10:08:21"
      },
      "SP95": {
        "valeur": "1.960",
        "maj": "2026-07-06 10:08:22"
      },
      "E85": {
        "valeur": "0.880",
        "maj": "2026-05-16 09:51:43"
      }
    }
  },
  {
    "id": "8210001",
    "dep": "08",
    "enseigne": "Esso",
    "adresse": "Avenue de la Paix",
    "cp": "08210",
    "ville": "MOUZON",
    "latitude": 49.61023,
    "longitude": 5.07788,
    "carburants": {
      "Gazole": {
        "valeur": "1.998",
        "maj": "2026-07-02 07:09:18"
      },
      "E10": {
        "valeur": "2.010",
        "maj": "2026-07-02 07:09:36"
      },
      "SP98": {
        "valeur": "2.140",
        "maj": "2026-07-02 07:09:54"
      }
    }
  },
  {
    "id": "8200005",
    "dep": "08",
    "enseigne": "Leclerc",
    "adresse": "14 Avenue Pasteur",
    "cp": "08200",
    "ville": "Sedan",
    "latitude": 49.699,
    "longitude": 4.928,
    "carburants": {
      "Gazole": {
        "valeur": "1.993",
        "maj": "2026-07-11 01:17:00"
      },
      "GPLc": {
        "valeur": "0.995",
        "maj": "2026-07-11 01:17:00"
      },
      "E10": {
        "valeur": "1.914",
        "maj": "2026-07-11 01:17:00"
      }
    }
  },
  {
    "id": "8000007",
    "dep": "08",
    "enseigne": "Intermarché",
    "adresse": "69 Rue de Monthermé",
    "cp": "08000",
    "ville": "Charleville-Mézières",
    "latitude": 49.785,
    "longitude": 4.713,
    "carburants": {
      "Gazole": {
        "valeur": "2.035",
        "maj": "2026-07-10 08:15:03"
      },
      "E10": {
        "valeur": "1.968",
        "maj": "2026-07-10 08:15:03"
      },
      "SP98": {
        "valeur": "2.055",
        "maj": "2026-07-09 07:48:43"
      }
    }
  },
  {
    "id": "8230001",
    "dep": "08",
    "enseigne": "Carrefour Market",
    "adresse": "Route de la Petite Chapelle",
    "cp": "08230",
    "ville": "ROCROI",
    "latitude": 49.928,
    "longitude": 4.526,
    "carburants": {
      "Gazole": {
        "valeur": "1.899",
        "maj": "2026-07-10 12:07:27"
      },
      "SP95": {
        "valeur": "1.975",
        "maj": "2026-07-10 12:07:27"
      },
      "SP98": {
        "valeur": "2.017",
        "maj": "2026-07-10 12:07:27"
      }
    }
  },
  {
    "id": "8400002",
    "dep": "08",
    "enseigne": "Esso Express",
    "adresse": "Rd 976, Chestres",
    "cp": "08400",
    "ville": "Vouziers",
    "latitude": 49.398687170482,
    "longitude": 4.715634421409,
    "carburants": {
      "Gazole": {
        "valeur": "1.981",
        "maj": "2026-07-10 07:31:00"
      },
      "E10": {
        "valeur": "1.955",
        "maj": "2026-07-10 07:31:00"
      },
      "SP98": {
        "valeur": "2.066",
        "maj": "2026-07-10 07:31:00"
      }
    }
  },
  {
    "id": "8000011",
    "dep": "08",
    "enseigne": "Système U",
    "adresse": "RD 764",
    "cp": "08000",
    "ville": "VILLERS-SEMEUSE",
    "latitude": 49.733,
    "longitude": 4.753,
    "carburants": {
      "Gazole": {
        "valeur": "2.035",
        "maj": "2026-07-10 10:14:27"
      },
      "E85": {
        "valeur": "0.780",
        "maj": "2026-07-10 10:14:27"
      },
      "GPLc": {
        "valeur": "0.999",
        "maj": "2026-07-10 10:14:27"
      },
      "E10": {
        "valeur": "1.968",
        "maj": "2026-07-10 10:14:27"
      },
      "SP98": {
        "valeur": "2.039",
        "maj": "2026-07-10 10:14:27"
      }
    }
  },
  {
    "id": "8170005",
    "dep": "08",
    "enseigne": "TotalEnergies",
    "adresse": "RN 51",
    "cp": "08170",
    "ville": "FUMAY",
    "latitude": 49.99467113949,
    "longitude": 4.6971376513648,
    "carburants": {
      "Gazole": {
        "valeur": "1.990",
        "maj": "2026-07-09 13:17:50"
      },
      "E10": {
        "valeur": "1.990",
        "maj": "2026-07-09 13:17:50"
      }
    }
  },
  {
    "id": "8320002",
    "dep": "08",
    "enseigne": "Intermarché",
    "adresse": "140 Avenue Roger Posty",
    "cp": "08320",
    "ville": "VIREUX-MOLHAIN",
    "latitude": 50.081,
    "longitude": 4.725,
    "carburants": {
      "Gazole": {
        "valeur": "1.999",
        "maj": "2026-07-10 23:59:00"
      },
      "E85": {
        "valeur": "0.809",
        "maj": "2026-07-10 23:59:00"
      },
      "E10": {
        "valeur": "1.919",
        "maj": "2026-07-10 23:59:00"
      },
      "SP98": {
        "valeur": "2.031",
        "maj": "2026-07-10 23:59:00"
      }
    }
  },
  {
    "id": "8360003",
    "dep": "08",
    "enseigne": "Carrefour Contact",
    "adresse": "37 Rue de la Sommevue",
    "cp": "08360",
    "ville": "Château-Porcien",
    "latitude": 49.53,
    "longitude": 4.249,
    "carburants": {
      "Gazole": {
        "valeur": "1.929",
        "maj": "2026-07-09 20:05:08"
      },
      "SP95": {
        "valeur": "1.949",
        "maj": "2026-07-09 20:05:08"
      },
      "SP98": {
        "valeur": "2.119",
        "maj": "2026-07-09 20:05:08"
      }
    }
  },
  {
    "id": "8350002",
    "dep": "08",
    "enseigne": "Carrefour Express",
    "adresse": "Rue Georges Clemenceau",
    "cp": "08350",
    "ville": "DONCHERY",
    "latitude": 49.698,
    "longitude": 4.866,
    "carburants": {
      "Gazole": {
        "valeur": "1.919",
        "maj": "2026-07-06 11:51:13"
      },
      "SP95": {
        "valeur": "1.955",
        "maj": "2026-07-06 11:51:13"
      },
      "SP98": {
        "valeur": "2.039",
        "maj": "2026-07-06 11:51:13"
      }
    }
  },
  {
    "id": "8320003",
    "dep": "08",
    "enseigne": "Indépendant sans enseigne",
    "adresse": "ROUTE NATIONALE 51",
    "cp": "08320",
    "ville": "HIERGES",
    "latitude": 50.106,
    "longitude": 4.743,
    "carburants": {
      "Gazole": {
        "valeur": "1.950",
        "maj": "2026-07-08 17:52:15"
      },
      "E85": {
        "valeur": "0.895",
        "maj": "2026-06-23 10:26:17"
      },
      "E10": {
        "valeur": "1.968",
        "maj": "2026-07-08 17:52:31"
      }
    }
  },
  {
    "id": "8170001",
    "dep": "08",
    "enseigne": "Carrefour Market",
    "adresse": "225 rue des evignes",
    "cp": "08170",
    "ville": "FUMAY",
    "latitude": 49.989,
    "longitude": 4.692,
    "carburants": {
      "Gazole": {
        "valeur": "1.910",
        "maj": "2026-07-09 12:21:50"
      },
      "SP95": {
        "valeur": "1.970",
        "maj": "2026-07-09 12:21:50"
      },
      "SP98": {
        "valeur": "2.010",
        "maj": "2026-07-09 12:21:50"
      }
    }
  },
  {
    "id": "8300008",
    "dep": "08",
    "enseigne": "TotalEnergies Access",
    "adresse": "4 RUE DE MONTPELLIER",
    "cp": "08300",
    "ville": "RETHEL",
    "latitude": 49.504,
    "longitude": 4.36,
    "carburants": {
      "Gazole": {
        "valeur": "1.984",
        "maj": "2026-07-11 00:01:00"
      },
      "E85": {
        "valeur": "0.822",
        "maj": "2026-07-11 00:01:00"
      },
      "E10": {
        "valeur": "1.919",
        "maj": "2026-07-11 00:01:00"
      }
    }
  },
  {
    "id": "8240001",
    "dep": "08",
    "enseigne": "TotalEnergies",
    "adresse": "15 RUE DE LA GARE",
    "cp": "08240",
    "ville": "BAR-LES-BUZANCY",
    "latitude": 49.42885798381901,
    "longitude": 4.9518145930264,
    "carburants": {
      "Gazole": {
        "valeur": "1.990",
        "maj": "2026-06-18 11:56:56"
      },
      "SP95": {
        "valeur": "1.990",
        "maj": "2026-06-18 11:56:56"
      }
    }
  },
  {
    "id": "8200010",
    "dep": "08",
    "enseigne": "TotalEnergies Access",
    "adresse": "8 AVENUE DE LA MARNE",
    "cp": "08200",
    "ville": "SEDAN",
    "latitude": 49.69926,
    "longitude": 4.92701,
    "carburants": {}
  },
  {
    "id": "8140003",
    "dep": "08",
    "enseigne": "Intermarché",
    "adresse": "centre commercial Mac Mahon route Nationale",
    "cp": "08140",
    "ville": "Bazeilles",
    "latitude": 49.684552690437,
    "longitude": 4.9723654981651,
    "carburants": {
      "Gazole": {
        "valeur": "1.989",
        "maj": "2026-07-10 13:15:05"
      },
      "GPLc": {
        "valeur": "0.999",
        "maj": "2026-04-27 11:28:50"
      },
      "E10": {
        "valeur": "1.929",
        "maj": "2026-07-10 10:55:51"
      },
      "SP98": {
        "valeur": "1.999",
        "maj": "2026-07-10 10:55:51"
      }
    }
  },
  {
    "id": "8150002",
    "dep": "08",
    "enseigne": "Carrefour Contact",
    "adresse": "103 Avenue Martyrs de la Résistance",
    "cp": "08150",
    "ville": "Renwez",
    "latitude": 49.84,
    "longitude": 4.605,
    "carburants": {
      "Gazole": {
        "valeur": "1.966",
        "maj": "2026-07-10 11:42:23"
      },
      "E10": {
        "valeur": "1.925",
        "maj": "2026-07-10 11:42:23"
      },
      "SP98": {
        "valeur": "2.069",
        "maj": "2026-07-10 11:42:24"
      }
    }
  },
  {
    "id": "8120001",
    "dep": "08",
    "enseigne": "Intermarché",
    "adresse": "63 Avenue Blanqui",
    "cp": "08120",
    "ville": "BOGNY-SUR-MEUSE",
    "latitude": 49.857,
    "longitude": 4.764,
    "carburants": {
      "Gazole": {
        "valeur": "2.035",
        "maj": "2026-07-10 08:55:01"
      },
      "E85": {
        "valeur": "0.809",
        "maj": "2026-06-12 09:08:52"
      },
      "E10": {
        "valeur": "1.957",
        "maj": "2026-07-10 08:55:01"
      },
      "SP98": {
        "valeur": "2.058",
        "maj": "2026-07-08 08:51:08"
      }
    }
  },
  {
    "id": "8110002",
    "dep": "08",
    "enseigne": "Intermarché",
    "adresse": "ZAC DE Wé - 2 avenue de l'Europe",
    "cp": "08110",
    "ville": "CARIGNAN - Wé",
    "latitude": 49.637,
    "longitude": 5.162,
    "carburants": {
      "Gazole": {
        "valeur": "1.912",
        "maj": "2026-07-09 19:00:00"
      },
      "SP95": {
        "valeur": "1.978",
        "maj": "2026-07-09 19:00:00"
      },
      "E85": {
        "valeur": "0.809",
        "maj": "2026-06-11 19:00:00"
      },
      "E10": {
        "valeur": "1.891",
        "maj": "2026-07-06 19:00:00"
      },
      "SP98": {
        "valeur": "2.020",
        "maj": "2026-07-09 19:00:00"
      }
    }
  },
  {
    "id": "8130004",
    "dep": "08",
    "enseigne": "TotalEnergies",
    "adresse": "5 ROUTE DE CHARLEVILLE",
    "cp": "08130",
    "ville": "Attigny",
    "latitude": 49.485,
    "longitude": 4.581,
    "carburants": {
      "Gazole": {
        "valeur": "1.990",
        "maj": "2026-06-25 22:10:00"
      },
      "E10": {
        "valeur": "1.990",
        "maj": "2026-07-03 14:07:48"
      },
      "SP98": {
        "valeur": "1.990",
        "maj": "2026-06-22 09:10:46"
      }
    }
  },
  {
    "id": "8200004",
    "dep": "08",
    "enseigne": "Esso Express",
    "adresse": "45 Avenue de la Marne",
    "cp": "08200",
    "ville": "Sedan",
    "latitude": 49.697,
    "longitude": 4.919,
    "carburants": {
      "Gazole": {
        "valeur": "1.925",
        "maj": "2026-07-10 07:50:00"
      },
      "E85": {
        "valeur": "0.933",
        "maj": "2026-07-10 07:50:00"
      },
      "E10": {
        "valeur": "1.907",
        "maj": "2026-07-10 07:50:00"
      },
      "SP98": {
        "valeur": "2.007",
        "maj": "2026-07-10 07:50:00"
      }
    }
  },
  {
    "id": "8270002",
    "dep": "08",
    "enseigne": "TotalEnergies",
    "adresse": "AUTOROUTE A34 - AIRE DES ARDENNES - WOINIC",
    "cp": "08270",
    "ville": "Saulces-Monclin",
    "latitude": 49.594069537325,
    "longitude": 4.5029188207464,
    "carburants": {
      "Gazole": {
        "valeur": "1.990",
        "maj": "2026-07-11 00:01:00"
      },
      "E85": {
        "valeur": "0.999",
        "maj": "2026-07-11 00:01:00"
      },
      "GPLc": {
        "valeur": "1.084",
        "maj": "2026-07-11 00:01:00"
      },
      "E10": {
        "valeur": "1.990",
        "maj": "2026-07-11 00:01:00"
      },
      "SP98": {
        "valeur": "1.990",
        "maj": "2026-07-11 00:01:00"
      }
    }
  },
  {
    "id": "8000005",
    "dep": "08",
    "enseigne": "Esso Express",
    "adresse": "17 Avenue Charles de Gaulle",
    "cp": "08000",
    "ville": "Charleville-Mézières",
    "latitude": 49.767,
    "longitude": 4.718,
    "carburants": {
      "Gazole": {
        "valeur": "1.933",
        "maj": "2026-07-09 17:10:00"
      },
      "E10": {
        "valeur": "1.966",
        "maj": "2026-07-09 17:10:00"
      },
      "SP98": {
        "valeur": "2.046",
        "maj": "2026-07-09 17:10:00"
      }
    }
  },
  {
    "id": "8000002",
    "dep": "08",
    "enseigne": "Supermarché Match",
    "adresse": "42 Avenue des Martyrs-de-la-Résistance",
    "cp": "08000",
    "ville": "Charleville-Mézières",
    "latitude": 49.75869,
    "longitude": 4.72653,
    "carburants": {
      "Gazole": {
        "valeur": "2.035",
        "maj": "2026-07-10 10:40:37"
      },
      "E10": {
        "valeur": "1.968",
        "maj": "2026-07-10 10:40:37"
      },
      "SP98": {
        "valeur": "2.055",
        "maj": "2026-07-10 10:40:37"
      }
    }
  },
  {
    "id": "8430001",
    "dep": "08",
    "enseigne": "Indépendant sans enseigne",
    "adresse": "32 GRANDE RUE",
    "cp": "08430",
    "ville": "POIX-TERRON",
    "latitude": 49.651,
    "longitude": 4.642,
    "carburants": {
      "Gazole": {
        "valeur": "1.999",
        "maj": "2026-07-07 13:51:38"
      },
      "E10": {
        "valeur": "2.032",
        "maj": "2026-06-23 16:29:34"
      },
      "SP98": {
        "valeur": "2.105",
        "maj": "2026-06-23 16:29:34"
      }
    }
  },
  {
    "id": "8600003",
    "dep": "08",
    "enseigne": "Intermarché",
    "adresse": "Route de Beauraing",
    "cp": "08600",
    "ville": "GIVET",
    "latitude": 50.134,
    "longitude": 4.854,
    "carburants": {
      "Gazole": {
        "valeur": "1.950",
        "maj": "2026-07-10 07:35:04"
      },
      "E85": {
        "valeur": "0.809",
        "maj": "2026-06-12 15:43:01"
      },
      "E10": {
        "valeur": "1.928",
        "maj": "2026-07-10 07:35:04"
      },
      "SP98": {
        "valeur": "1.992",
        "maj": "2026-07-04 20:22:18"
      }
    }
  },
  {
    "id": "8150001",
    "dep": "08",
    "enseigne": "Carrefour Contact",
    "adresse": "RUE PASTEUR",
    "cp": "08150",
    "ville": "RIMOGNE",
    "latitude": 49.84,
    "longitude": 4.545,
    "carburants": {
      "Gazole": {
        "valeur": "1.924",
        "maj": "2026-07-10 16:51:44"
      },
      "SP95": {
        "valeur": "1.945",
        "maj": "2026-07-02 10:24:26"
      },
      "E85": {
        "valeur": "0.815",
        "maj": "2026-07-02 10:24:26"
      },
      "SP98": {
        "valeur": "2.022",
        "maj": "2026-07-02 10:24:26"
      }
    }
  },
  {
    "id": "8300006",
    "dep": "08",
    "enseigne": "Intermarché",
    "adresse": "24 Rue de Reims",
    "cp": "08300",
    "ville": "SAULT-LèS-RETHEL",
    "latitude": 49.50033,
    "longitude": 4.35794,
    "carburants": {
      "Gazole": {
        "valeur": "2.009",
        "maj": "2026-07-10 08:08:00"
      },
      "E85": {
        "valeur": "0.809",
        "maj": "2026-07-10 08:08:05"
      },
      "E10": {
        "valeur": "1.925",
        "maj": "2026-07-10 08:08:12"
      },
      "SP98": {
        "valeur": "1.995",
        "maj": "2026-07-10 08:08:18"
      }
    }
  },
  {
    "id": "8300007",
    "dep": "08",
    "enseigne": "Intermarché",
    "adresse": "Rue Arthur Rimbaud",
    "cp": "08300",
    "ville": "AMAGNE",
    "latitude": 49.51743,
    "longitude": 4.49483,
    "carburants": {
      "Gazole": {
        "valeur": "1.899",
        "maj": "2026-07-07 08:22:32"
      },
      "E10": {
        "valeur": "1.909",
        "maj": "2026-07-07 08:22:32"
      },
      "SP98": {
        "valeur": "2.039",
        "maj": "2026-07-07 08:22:32"
      }
    }
  },
  {
    "id": "8500002",
    "dep": "08",
    "enseigne": "Intermarché",
    "adresse": "13 Avenue Danton",
    "cp": "08500",
    "ville": "REVIN",
    "latitude": 49.939,
    "longitude": 4.641,
    "carburants": {
      "Gazole": {
        "valeur": "1.923",
        "maj": "2026-07-10 07:52:00"
      },
      "E10": {
        "valeur": "1.941",
        "maj": "2026-07-10 07:52:00"
      }
    }
  },
  {
    "id": "8400004",
    "dep": "08",
    "enseigne": "Carrefour Market",
    "adresse": "Rue Verte",
    "cp": "08400",
    "ville": "VOUZIERS",
    "latitude": 49.405,
    "longitude": 4.697,
    "carburants": {
      "Gazole": {
        "valeur": "1.969",
        "maj": "2026-07-10 12:09:09"
      },
      "SP95": {
        "valeur": "1.979",
        "maj": "2026-07-10 12:09:09"
      },
      "E10": {
        "valeur": "1.959",
        "maj": "2026-07-10 12:09:09"
      },
      "SP98": {
        "valeur": "2.029",
        "maj": "2026-07-10 12:09:09"
      }
    }
  },
  {
    "id": "8800004",
    "dep": "08",
    "enseigne": "Carrefour Contact",
    "adresse": "RUE ANDRE COMPAIN",
    "cp": "08800",
    "ville": "MONTHERME",
    "latitude": 49.885,
    "longitude": 4.739,
    "carburants": {
      "Gazole": {
        "valeur": "2.041",
        "maj": "2026-07-10 09:37:38"
      },
      "SP95": {
        "valeur": "2.022",
        "maj": "2026-07-10 09:37:38"
      },
      "SP98": {
        "valeur": "2.080",
        "maj": "2026-07-10 09:37:38"
      }
    }
  },
  {
    "id": "8400003",
    "dep": "08",
    "enseigne": "Leclerc",
    "adresse": "115 rue Bournizet",
    "cp": "08400",
    "ville": "VOUZIERS",
    "latitude": 49.396,
    "longitude": 4.682,
    "carburants": {
      "Gazole": {
        "valeur": "1.964",
        "maj": "2026-07-11 01:18:00"
      },
      "SP95": {
        "valeur": "1.983",
        "maj": "2026-07-11 01:18:00"
      },
      "E85": {
        "valeur": "0.776",
        "maj": "2026-07-11 01:18:00"
      },
      "E10": {
        "valeur": "1.959",
        "maj": "2026-07-11 01:18:00"
      },
      "SP98": {
        "valeur": "2.025",
        "maj": "2026-07-11 01:18:00"
      }
    }
  },
  {
    "id": "8000001",
    "dep": "08",
    "enseigne": "Carrefour",
    "adresse": "1 rue Paulin Richier",
    "cp": "08000",
    "ville": "CHARLEVILLE-MéZIèRES",
    "latitude": 49.739,
    "longitude": 4.707,
    "carburants": {
      "Gazole": {
        "valeur": "2.000",
        "maj": "2026-07-10 22:41:00"
      },
      "SP95": {
        "valeur": "2.017",
        "maj": "2026-07-10 22:41:00"
      },
      "E85": {
        "valeur": "0.780",
        "maj": "2026-07-10 22:41:00"
      },
      "GPLc": {
        "valeur": "0.999",
        "maj": "2026-07-10 22:41:00"
      },
      "E10": {
        "valeur": "1.968",
        "maj": "2026-07-10 22:41:00"
      },
      "SP98": {
        "valeur": "2.039",
        "maj": "2026-07-10 22:41:00"
      }
    }
  },
  {
    "id": "8260002",
    "dep": "08",
    "enseigne": "Intermarché Contact",
    "adresse": "RN43 Lieu dit Le Pré Meumon",
    "cp": "08260",
    "ville": "Maubert-Fontaine",
    "latitude": 49.867,
    "longitude": 4.428,
    "carburants": {
      "Gazole": {
        "valeur": "1.924",
        "maj": "2026-07-09 13:17:43"
      },
      "E85": {
        "valeur": "0.809",
        "maj": "2026-06-11 15:43:39"
      },
      "E10": {
        "valeur": "1.926",
        "maj": "2026-07-09 13:17:43"
      },
      "SP98": {
        "valeur": "2.033",
        "maj": "2026-07-09 13:17:43"
      }
    }
  },
  {
    "id": "8200007",
    "dep": "08",
    "enseigne": "Intermarché",
    "adresse": "Rue Cadeau",
    "cp": "08200",
    "ville": "SEDAN",
    "latitude": 49.706,
    "longitude": 4.936,
    "carburants": {
      "Gazole": {
        "valeur": "1.929",
        "maj": "2026-07-10 12:21:50"
      },
      "E10": {
        "valeur": "1.915",
        "maj": "2026-07-09 12:51:33"
      },
      "SP98": {
        "valeur": "1.999",
        "maj": "2026-07-08 07:43:32"
      }
    }
  },
  {
    "id": "8300001",
    "dep": "08",
    "enseigne": "Carrefour",
    "adresse": "ZONE DE L'ETOILE",
    "cp": "08300",
    "ville": "Rethel",
    "latitude": 49.511,
    "longitude": 4.368,
    "carburants": {
      "Gazole": {
        "valeur": "2.000",
        "maj": "2026-07-11 00:41:00"
      },
      "E10": {
        "valeur": "1.962",
        "maj": "2026-07-11 00:41:00"
      },
      "SP98": {
        "valeur": "2.081",
        "maj": "2026-07-11 00:41:00"
      }
    }
  },
  {
    "id": "8800001",
    "dep": "08",
    "enseigne": "TotalEnergies",
    "adresse": "Rue André Compain",
    "cp": "08800",
    "ville": "Monthermé",
    "latitude": 49.88,
    "longitude": 4.742,
    "carburants": {
      "Gazole": {
        "valeur": "1.990",
        "maj": "2026-07-01 07:27:54"
      },
      "E10": {
        "valeur": "1.990",
        "maj": "2026-07-01 07:27:54"
      }
    }
  },
  {
    "id": "8190003",
    "dep": "08",
    "enseigne": "Carrefour Contact",
    "adresse": "1 Rue Chantereine",
    "cp": "08190",
    "ville": "Asfeld",
    "latitude": 49.47064,
    "longitude": 4.12341,
    "carburants": {
      "Gazole": {
        "valeur": "1.990",
        "maj": "2026-07-10 11:10:24"
      },
      "SP95": {
        "valeur": "1.970",
        "maj": "2026-07-10 11:10:24"
      },
      "SP98": {
        "valeur": "2.020",
        "maj": "2026-07-10 11:10:24"
      }
    }
  },
  {
    "id": "8460001",
    "dep": "08",
    "enseigne": "TotalEnergies Contact",
    "adresse": "1 route de rocroi",
    "cp": "08460",
    "ville": "signy l'abbaye",
    "latitude": 49.699763,
    "longitude": 4.4230659999999995,
    "carburants": {
      "Gazole": {
        "valeur": "1.976",
        "maj": "2026-06-24 06:41:56"
      },
      "SP95": {
        "valeur": "1.990",
        "maj": "2026-06-15 17:05:17"
      },
      "SP98": {
        "valeur": "1.990",
        "maj": "2026-06-15 17:05:17"
      }
    }
  },
  {
    "id": "8000008",
    "dep": "08",
    "enseigne": "Intermarché",
    "adresse": "197 Avenue Carnot",
    "cp": "08000",
    "ville": "Charleville-Mézières",
    "latitude": 49.746,
    "longitude": 4.727,
    "carburants": {
      "Gazole": {
        "valeur": "1.999",
        "maj": "2026-07-10 07:54:49"
      },
      "E85": {
        "valeur": "0.809",
        "maj": "2026-06-12 07:47:48"
      },
      "E10": {
        "valeur": "1.957",
        "maj": "2026-07-08 08:07:37"
      },
      "SP98": {
        "valeur": "2.055",
        "maj": "2026-07-08 08:07:38"
      }
    }
  },
  {
    "id": "8110005",
    "dep": "08",
    "enseigne": "Carrefour Market",
    "adresse": "43 Route Nationale",
    "cp": "08110",
    "ville": "Blagny",
    "latitude": 49.621550437047,
    "longitude": 5.1862764178631,
    "carburants": {
      "Gazole": {
        "valeur": "1.887",
        "maj": "2026-07-09 08:56:52"
      },
      "E10": {
        "valeur": "1.890",
        "maj": "2026-07-09 08:56:52"
      },
      "SP98": {
        "valeur": "1.999",
        "maj": "2026-07-09 08:56:52"
      }
    }
  },
  {
    "id": "8700004",
    "dep": "08",
    "enseigne": "Carrefour Market",
    "adresse": "42 RUE PARMENTIER",
    "cp": "08700",
    "ville": "NOUZONVILLE",
    "latitude": 49.822185722569,
    "longitude": 4.7429365808471005,
    "carburants": {
      "Gazole": {
        "valeur": "1.919",
        "maj": "2026-07-08 07:38:53"
      },
      "SP95": {
        "valeur": "1.999",
        "maj": "2026-06-19 12:33:54"
      },
      "SP98": {
        "valeur": "2.099",
        "maj": "2026-06-12 11:05:44"
      }
    }
  },
  {
    "id": "8190001",
    "dep": "08",
    "enseigne": "TotalEnergies",
    "adresse": "70 Rue Chantereine",
    "cp": "08190",
    "ville": "ASFELD",
    "latitude": 49.465,
    "longitude": 4.112,
    "carburants": {
      "Gazole": {
        "valeur": "1.990",
        "maj": "2026-07-07 07:28:25"
      },
      "E10": {
        "valeur": "1.990",
        "maj": "2026-07-07 07:28:25"
      },
      "SP98": {
        "valeur": "1.990",
        "maj": "2026-07-07 07:28:25"
      }
    }
  },
  {
    "id": "8000010",
    "dep": "08",
    "enseigne": "TotalEnergies",
    "adresse": "RTE DE LAFRANCHEVILLE",
    "cp": "08000",
    "ville": "Charleville-Mézières",
    "latitude": 49.741,
    "longitude": 4.726,
    "carburants": {
      "Gazole": {
        "valeur": "2.104",
        "maj": "2026-07-11 00:01:00"
      },
      "E85": {
        "valeur": "0.831",
        "maj": "2026-07-11 00:01:00"
      },
      "GPLc": {
        "valeur": "0.985",
        "maj": "2026-07-11 00:01:00"
      },
      "E10": {
        "valeur": "1.990",
        "maj": "2026-07-11 00:01:00"
      }
    }
  }
]