{
  "departement": "18",
  "date": "2026-05-02",
  "stations": [
    {
      "id": "18200011",
      "lat": 46.752,
      "lon": 2.416,
      "cp": "18200",
      "ville": "FARGE ALLICHAMPS",
      "prix": {
        "Gazole": 0.002367,
        "GPLc": 0.001119,
        "E10": 0.0021669999999999997,
        "SP98": 0.002267
      },
      "maj_gouv": {
        "Gazole": "2026-05-01 07:46:00",
        "GPLc": "2026-05-01 07:46:00",
        "E10": "2026-05-01 07:46:00",
        "SP98": "2026-05-01 07:46:00"
      }
    },
    {
      "id": "18390004",
      "lat": 47.099,
      "lon": 2.489,
      "cp": "18390",
      "ville": "Saint-germain-du-puy",
      "prix": {
        "Gazole": 0.002229,
        "E85": 0.000819,
        "E10": 0.001999
      },
      "maj_gouv": {
        "Gazole": "2026-04-30 08:19:26",
        "E85": "2026-04-15 09:28:03",
        "E10": "2026-04-30 08:19:26"
      }
    },
    {
      "id": "18600003",
      "lat": 46.833,
      "lon": 2.938,
      "cp": "18600",
      "ville": "SANCOINS",
      "prix": {
        "Gazole": 0.002195,
        "SP95": 0.002075,
        "SP98": 0.002129
      },
      "maj_gouv": {
        "Gazole": "2026-04-30 05:24:17",
        "SP95": "2026-04-30 05:24:18",
        "SP98": "2026-04-30 05:24:18"
      }
    },
    {
      "id": "18000001",
      "lat": 47.103,
      "lon": 2.41,
      "cp": "18000",
      "ville": "BOURGES",
      "prix": {
        "Gazole": 0.0024,
        "SP95": 0.0021000000000000003,
        "SP98": 0.0021349999999999997
      },
      "maj_gouv": {
        "Gazole": "2026-04-29 11:20:44",
        "SP95": "2026-04-29 11:20:44",
        "SP98": "2026-04-29 11:20:44"
      }
    },
    {
      "id": "18000021",
      "lat": 47.082,
      "lon": 2.365,
      "cp": "18000",
      "ville": "BOURGES",
      "prix": {
        "Gazole": 0.002177,
        "E85": 0.0008179999999999999,
        "E10": 0.001982,
        "SP98": 0.002068
      },
      "maj_gouv": {
        "Gazole": "2026-04-30 08:44:46",
        "E85": "2026-04-30 08:44:46",
        "E10": "2026-04-30 08:44:46",
        "SP98": "2026-04-30 08:44:46"
      }
    },
    {
      "id": "18200002",
      "lat": 46.726,
      "lon": 2.503,
      "cp": "18200",
      "ville": "Saint-Amand-Montrond",
      "prix": {
        "Gazole": 0.00225,
        "SP95": 0.00199
      },
      "maj_gouv": {
        "Gazole": "2026-04-27 08:51:43",
        "SP95": "2026-04-22 08:05:28"
      }
    },
    {
      "id": "18700003",
      "lat": 47.498,
      "lon": 2.441,
      "cp": "18700",
      "ville": "AUBIGNY-SUR-NERE",
      "prix": {
        "Gazole": 0.002169,
        "E85": 0.0008179999999999999,
        "E10": 0.0019790000000000003,
        "SP98": 0.002089
      },
      "maj_gouv": {
        "Gazole": "2026-04-28 08:04:49",
        "E85": "2026-04-25 08:44:36",
        "E10": "2026-04-28 08:04:49",
        "SP98": "2026-04-25 08:44:36"
      }
    },
    {
      "id": "18000002",
      "lat": 47.093,
      "lon": 2.428,
      "cp": "18000",
      "ville": "BOURGES",
      "prix": {
        "Gazole": 0.0021920000000000004,
        "SP95": 0.002062,
        "E10": 0.0020139999999999997,
        "SP98": 0.002148
      },
      "maj_gouv": {
        "Gazole": "2026-04-30 08:50:02",
        "SP95": "2026-04-30 08:50:03",
        "E10": "2026-04-30 08:50:03",
        "SP98": "2026-04-30 08:50:03"
      }
    },
    {
      "id": "18200009",
      "lat": 46.724,
      "lon": 2.461,
      "cp": "18200",
      "ville": "Orval",
      "prix": {
        "Gazole": 0.00219,
        "E85": 0.0008179999999999999,
        "E10": 0.0020499999999999997
      },
      "maj_gouv": {
        "Gazole": "2026-04-29 09:13:16",
        "E85": "2026-04-25 09:15:00",
        "E10": "2026-04-25 09:15:00"
      }
    },
    {
      "id": "18000016",
      "lat": 47.079,
      "lon": 2.389,
      "cp": "18000",
      "ville": "BOURGES",
      "prix": {
        "Gazole": 0.0022389999999999997,
        "E10": 0.002089,
        "SP98": 0.0022589999999999997
      },
      "maj_gouv": {
        "Gazole": "2026-05-01 11:28:22",
        "E10": "2026-05-01 11:28:22",
        "SP98": "2026-05-01 11:28:22"
      }
    },
    {
      "id": "18170001",
      "lat": 46.642,
      "lon": 2.284,
      "cp": "18170",
      "ville": "Le Châtelet",
      "prix": {
        "Gazole": 0.002159,
        "SP95": 0.00204,
        "SP98": 0.002129
      },
      "maj_gouv": {
        "Gazole": "2026-04-29 12:38:24",
        "SP95": "2026-04-22 10:35:52",
        "SP98": "2026-04-22 10:35:52"
      }
    },
    {
      "id": "18100016",
      "lat": 47.222,
      "lon": 2.069,
      "cp": "18100",
      "ville": "Vierzon",
      "prix": {
        "Gazole": 0.002195,
        "E10": 0.001998,
        "SP98": 0.002075
      },
      "maj_gouv": {
        "Gazole": "2026-04-16 14:36:08",
        "E10": "2026-04-27 16:05:39",
        "SP98": "2026-04-27 16:05:39"
      }
    },
    {
      "id": "18190001",
      "lat": 46.86,
      "lon": 2.328,
      "cp": "18190",
      "ville": "CHATEAUNEUF-SUR-CHER",
      "prix": {
        "Gazole": 0.002169,
        "SP95": 0.002049,
        "E10": 0.001999
      },
      "maj_gouv": {
        "Gazole": "2026-04-30 07:33:39",
        "SP95": "2026-04-30 07:33:40",
        "E10": "2026-04-30 07:33:40"
      }
    },
    {
      "id": "18300006",
      "lat": 47.32481951378,
      "lon": 2.8238587922201996,
      "cp": "18300",
      "ville": "SANCERRE",
      "prix": {
        "Gazole": 0.0022890000000000002,
        "SP95": 0.002128,
        "SP98": 0.002132
      },
      "maj_gouv": {
        "Gazole": "2026-05-01 12:22:21",
        "SP95": "2026-04-30 19:47:04",
        "SP98": "2026-04-14 18:29:13"
      }
    },
    {
      "id": "18350001",
      "lat": 46.998,
      "lon": 2.818,
      "cp": "18350",
      "ville": "NéRONDES",
      "prix": {
        "Gazole": 0.002199,
        "E10": 0.001999,
        "SP98": 0.0021190000000000002
      },
      "maj_gouv": {
        "Gazole": "2026-04-29 10:37:02",
        "E10": "2026-04-29 10:37:02",
        "SP98": "2026-04-29 10:37:02"
      }
    },
    {
      "id": "18110001",
      "lat": 47.210547849899996,
      "lon": 2.42521747273,
      "cp": "18110",
      "ville": "SAINT-MARTIN-D'AUXIGNY",
      "prix": {
        "Gazole": 0.002205,
        "SP95": 0.002045,
        "SP98": 0.002099
      },
      "maj_gouv": {
        "Gazole": "2026-04-30 09:48:52",
        "SP95": "2026-04-30 09:48:52",
        "SP98": "2026-04-30 09:48:52"
      }
    },
    {
      "id": "18000004",
      "lat": 47.07082,
      "lon": 2.37747,
      "cp": "18000",
      "ville": "BOURGES",
      "prix": {
        "Gazole": 0.002199,
        "SP95": 0.002088,
        "SP98": 0.002145
      },
      "maj_gouv": {
        "Gazole": "2026-04-24 07:27:08",
        "SP95": "2026-04-24 07:27:08",
        "SP98": "2026-04-24 07:27:08"
      }
    },
    {
      "id": "18140003",
      "lat": 47.156918787550005,
      "lon": 2.9110220760407004,
      "cp": "18140",
      "ville": "Sancergues",
      "prix": {},
      "maj_gouv": {}
    },
    {
      "id": "18240001",
      "lat": 47.505,
      "lon": 2.852,
      "cp": "18240",
      "ville": "Belleville-sur-Loire",
      "prix": {
        "Gazole": 0.002221,
        "E10": 0.0020499999999999997,
        "SP98": 0.002105
      },
      "maj_gouv": {
        "Gazole": "2026-04-29 09:19:14",
        "E10": "2026-04-29 09:19:14",
        "SP98": "2026-04-29 09:19:14"
      }
    },
    {
      "id": "18100017",
      "lat": 47.239786394848004,
      "lon": 2.0920474189544,
      "cp": "18100",
      "ville": "Vierzon",
      "prix": {
        "Gazole": 0.002195,
        "E85": 0.000855,
        "GPLc": 0.001078,
        "E10": 0.001999,
        "SP98": 0.002075
      },
      "maj_gouv": {
        "Gazole": "2026-04-29 08:20:45",
        "E85": "2026-04-29 08:20:46",
        "GPLc": "2026-04-11 09:59:02",
        "E10": "2026-04-27 08:07:03",
        "SP98": "2026-04-29 08:20:46"
      }
    },
    {
      "id": "18200005",
      "lat": 46.736,
      "lon": 2.491,
      "cp": "18200",
      "ville": "SAINT-AMAND-MONTROND",
      "prix": {
        "Gazole": 0.00219,
        "SP95": 0.0020499999999999997,
        "E10": 0.001999,
        "SP98": 0.002099
      },
      "maj_gouv": {
        "Gazole": "2026-04-29 09:12:54",
        "SP95": "2026-04-15 09:28:25",
        "E10": "2026-04-15 09:28:26",
        "SP98": "2026-04-07 09:15:00"
      }
    },
    {
      "id": "18350003",
      "lat": 46.896,
      "lon": 2.729,
      "cp": "18350",
      "ville": "BLET",
      "prix": {
        "Gazole": 0.00225,
        "SP95": 0.00199
      },
      "maj_gouv": {
        "Gazole": "2026-04-11 11:24:01",
        "SP95": "2026-04-11 11:24:01"
      }
    },
    {
      "id": "18000011",
      "lat": 47.065077699022005,
      "lon": 2.39756900796,
      "cp": "18000",
      "ville": "Bourges",
      "prix": {
        "Gazole": 0.002198,
        "E10": 0.0019790000000000003,
        "SP98": 0.002109
      },
      "maj_gouv": {
        "Gazole": "2026-04-29 09:51:16",
        "E10": "2026-04-29 09:51:16",
        "SP98": "2026-04-29 09:51:16"
      }
    },
    {
      "id": "18310003",
      "lat": 47.144119839116996,
      "lon": 1.8480204743653998,
      "cp": "18310",
      "ville": "Graçay",
      "prix": {
        "E10": 0.001933,
        "SP98": 0.002077
      },
      "maj_gouv": {
        "E10": "2026-04-22 08:24:20",
        "SP98": "2026-04-22 08:24:20"
      }
    },
    {
      "id": "18520001",
      "lat": 47.032,
      "lon": 2.642,
      "cp": "18520",
      "ville": "AVORD",
      "prix": {
        "Gazole": 0.002229,
        "E85": 0.0008179999999999999,
        "E10": 0.0020150000000000003,
        "SP98": 0.002128
      },
      "maj_gouv": {
        "Gazole": "2026-04-30 08:28:29",
        "E85": "2026-04-16 07:58:24",
        "E10": "2026-04-30 08:28:30",
        "SP98": "2026-04-30 08:28:30"
      }
    },
    {
      "id": "18000014",
      "lat": 47.067,
      "lon": 2.416,
      "cp": "18000",
      "ville": "Bourges",
      "prix": {
        "Gazole": 0.002169,
        "SP95": 0.002088,
        "E10": 0.001999,
        "SP98": 0.002099
      },
      "maj_gouv": {
        "Gazole": "2026-04-30 11:08:42",
        "SP95": "2026-04-13 12:29:40",
        "E10": "2026-04-30 11:08:42",
        "SP98": "2026-04-17 13:37:25"
      }
    },
    {
      "id": "18390003",
      "lat": 47.096,
      "lon": 2.441,
      "cp": "18390",
      "ville": "Saint-Germain-du-Puy",
      "prix": {
        "Gazole": 0.0022229999999999997,
        "GPLc": 0.001019,
        "E10": 0.001994,
        "SP98": 0.002141
      },
      "maj_gouv": {
        "Gazole": "2026-04-30 08:59:10",
        "GPLc": "2026-04-30 08:59:10",
        "E10": "2026-04-30 08:59:10",
        "SP98": "2026-04-30 08:59:10"
      }
    },
    {
      "id": "18100011",
      "lat": 47.227125767400004,
      "lon": 2.05324708161,
      "cp": "18100",
      "ville": "VIERZON",
      "prix": {
        "Gazole": 0.00209,
        "E85": 0.0008449999999999999,
        "GPLc": 0.0010789999999999999,
        "E10": 0.00199
      },
      "maj_gouv": {
        "Gazole": "2026-05-02 00:01:00",
        "E85": "2026-05-02 00:01:00",
        "GPLc": "2026-05-02 00:01:00",
        "E10": "2026-05-02 00:01:00"
      }
    },
    {
      "id": "18500007",
      "lat": 47.095,
      "lon": 2.24,
      "cp": "18500",
      "ville": "Marmagne",
      "prix": {
        "Gazole": 0.002326,
        "E10": 0.002149,
        "SP98": 0.002249
      },
      "maj_gouv": {
        "Gazole": "2026-05-01 07:46:00",
        "E10": "2026-05-01 07:46:00",
        "SP98": "2026-05-01 07:46:00"
      }
    },
    {
      "id": "18410002",
      "lat": 47.549,
      "lon": 2.448,
      "cp": "18410",
      "ville": "ARGENT-SUR-SAULDRE",
      "prix": {
        "Gazole": 0.002149,
        "E85": 0.000758,
        "E10": 0.0019890000000000003,
        "SP98": 0.002069
      },
      "maj_gouv": {
        "Gazole": "2026-04-25 09:02:57",
        "E85": "2026-04-25 09:02:57",
        "E10": "2026-04-30 11:17:19",
        "SP98": "2026-04-30 11:17:19"
      }
    },
    {
      "id": "18103001",
      "lat": 47.231,
      "lon": 2.088,
      "cp": "18100",
      "ville": "Vierzon",
      "prix": {
        "Gazole": 0.002165,
        "SP95": 0.002039,
        "E10": 0.0019790000000000003,
        "SP98": 0.002065
      },
      "maj_gouv": {
        "Gazole": "2026-04-30 08:27:06",
        "SP95": "2026-04-30 08:27:06",
        "E10": "2026-04-30 08:27:06",
        "SP98": "2026-04-30 08:27:06"
      }
    },
    {
      "id": "18240002",
      "lat": 47.421,
      "lon": 2.884,
      "cp": "18240",
      "ville": "Boulleret",
      "prix": {
        "Gazole": 0.00227,
        "E85": 0.00083,
        "E10": 0.00207
      },
      "maj_gouv": {
        "Gazole": "2026-04-29 23:50:00",
        "E85": "2026-04-26 23:50:00",
        "E10": "2026-04-29 23:50:00"
      }
    },
    {
      "id": "18370001",
      "lat": 46.555,
      "lon": 2.201,
      "cp": "18370",
      "ville": "Châteaumeillant",
      "prix": {
        "Gazole": 0.002199,
        "E85": 0.0008489999999999999,
        "E10": 0.002009,
        "SP98": 0.002099
      },
      "maj_gouv": {
        "Gazole": "2026-04-29 09:24:17",
        "E85": "2026-04-22 09:13:41",
        "E10": "2026-04-29 09:24:17",
        "SP98": "2026-04-16 11:47:50"
      }
    },
    {
      "id": "18000017",
      "lat": 47.094,
      "lon": 2.391,
      "cp": "18000",
      "ville": "BOURGES",
      "prix": {
        "Gazole": 0.00209,
        "E85": 0.000855,
        "GPLc": 0.0010329999999999998,
        "E10": 0.00199,
        "SP98": 0.00199
      },
      "maj_gouv": {
        "Gazole": "2026-05-02 00:01:00",
        "E85": "2026-05-02 00:01:00",
        "GPLc": "2026-05-02 00:01:00",
        "E10": "2026-05-02 00:01:00",
        "SP98": "2026-05-02 00:01:00"
      }
    },
    {
      "id": "18100015",
      "lat": 47.221473011548,
      "lon": 2.0652897018218,
      "cp": "18100",
      "ville": "VIERZON",
      "prix": {
        "Gazole": 0.002195,
        "SP95": 0.002049,
        "SP98": 0.002075
      },
      "maj_gouv": {
        "Gazole": "2026-04-28 16:54:12",
        "SP95": "2026-04-28 16:54:12",
        "SP98": "2026-04-28 16:54:12"
      }
    },
    {
      "id": "18250002",
      "lat": 47.3,
      "lon": 2.517,
      "cp": "18250",
      "ville": "HENRICHEMONT",
      "prix": {
        "Gazole": 0.002159,
        "E10": 0.001999,
        "SP98": 0.002109
      },
      "maj_gouv": {
        "Gazole": "2026-04-30 14:57:58",
        "E10": "2026-04-30 14:57:58",
        "SP98": "2026-04-30 14:57:58"
      }
    },
    {
      "id": "18150001",
      "lat": 46.951,
      "lon": 2.949,
      "cp": "18150",
      "ville": "LA GUERCHE SUR L AUBOIS",
      "prix": {
        "Gazole": 0.002399,
        "SP95": 0.002099,
        "SP98": 0.002149
      },
      "maj_gouv": {
        "Gazole": "2026-04-16 15:18:09",
        "SP95": "2026-04-16 15:17:06",
        "SP98": "2026-04-16 15:17:06"
      }
    },
    {
      "id": "18300001",
      "lat": 47.33375944,
      "lon": 2.8320786700000005,
      "cp": "18300",
      "ville": "SANCERRE",
      "prix": {
        "Gazole": 0.0022,
        "E85": 0.0008489999999999999,
        "SP98": 0.002128
      },
      "maj_gouv": {
        "Gazole": "2026-04-29 08:24:36",
        "E85": "2026-04-21 09:23:02",
        "SP98": "2026-04-29 08:24:36"
      }
    },
    {
      "id": "18000018",
      "lat": 47.072,
      "lon": 2.395,
      "cp": "18000",
      "ville": "BOURGES",
      "prix": {
        "Gazole": 0.00209,
        "E85": 0.000839
      },
      "maj_gouv": {
        "Gazole": "2026-05-02 00:01:00",
        "E85": "2026-05-02 00:01:00"
      }
    },
    {
      "id": "18800001",
      "lat": 47.082,
      "lon": 2.729,
      "cp": "18800",
      "ville": "BAUGY",
      "prix": {
        "Gazole": 0.0022890000000000002,
        "SP95": 0.002099,
        "SP98": 0.002199
      },
      "maj_gouv": {
        "Gazole": "2026-04-23 00:00:00",
        "SP95": "2026-04-15 00:00:00",
        "SP98": "2026-04-15 00:00:00"
      }
    },
    {
      "id": "18160001",
      "lat": 46.753,
      "lon": 2.169,
      "cp": "18160",
      "ville": "LIGNIèRES",
      "prix": {
        "Gazole": 0.0022389999999999997,
        "SP95": 0.002058,
        "E10": 0.001999,
        "SP98": 0.002148
      },
      "maj_gouv": {
        "Gazole": "2026-04-28 08:15:53",
        "SP95": "2026-04-28 08:15:53",
        "E10": "2026-04-28 08:15:53",
        "SP98": "2026-04-28 08:15:53"
      }
    },
    {
      "id": "18500008",
      "lat": 47.1501613,
      "lon": 2.2153735,
      "cp": "18500",
      "ville": "Mehun-sur-Yèvre",
      "prix": {
        "Gazole": 0.002199,
        "SP95": 0.002029,
        "SP98": 0.002059
      },
      "maj_gouv": {
        "Gazole": "2026-04-29 08:13:54",
        "SP95": "2026-04-23 12:11:26",
        "SP98": "2026-04-23 12:11:27"
      }
    },
    {
      "id": "18130002",
      "lat": 46.889,
      "lon": 2.569,
      "cp": "18130",
      "ville": "DUN-SUR-AURON",
      "prix": {
        "Gazole": 0.002199,
        "E10": 0.002005,
        "SP98": 0.002097
      },
      "maj_gouv": {
        "Gazole": "2026-04-27 15:15:58",
        "E10": "2026-04-27 15:15:58",
        "SP98": "2026-04-27 15:15:58"
      }
    },
    {
      "id": "18200001",
      "lat": 46.730351458895996,
      "lon": 2.4937252949649,
      "cp": "18200",
      "ville": "Saint-Amand-Montrond",
      "prix": {
        "Gazole": 0.00219,
        "SP95": 0.0020499999999999997,
        "SP98": 0.002179
      },
      "maj_gouv": {
        "Gazole": "2026-04-30 11:10:35",
        "SP95": "2026-04-18 13:03:50",
        "SP98": "2026-04-07 14:10:05"
      }
    },
    {
      "id": "18500004",
      "lat": 47.142,
      "lon": 2.243,
      "cp": "18500",
      "ville": "MEHUN-SUR-YèVRE",
      "prix": {
        "Gazole": 0.002179,
        "E85": 0.0008179999999999999,
        "E10": 0.001975,
        "SP98": 0.002068
      },
      "maj_gouv": {
        "Gazole": "2026-04-28 09:44:48",
        "E85": "2026-04-28 09:44:49",
        "E10": "2026-04-28 09:44:49",
        "SP98": "2026-04-28 09:44:49"
      }
    },
    {
      "id": "18600001",
      "lat": 46.836,
      "lon": 2.914,
      "cp": "18600",
      "ville": "SANCOINS",
      "prix": {
        "Gazole": 0.0022890000000000002,
        "SP95": 0.002099,
        "SP98": 0.002199
      },
      "maj_gouv": {
        "Gazole": "2026-04-23 00:00:00",
        "SP95": "2026-04-15 00:00:00",
        "SP98": "2026-04-15 00:00:00"
      }
    },
    {
      "id": "18130001",
      "lat": 46.885,
      "lon": 2.569,
      "cp": "18130",
      "ville": "DUN-SUR-AURON",
      "prix": {
        "Gazole": 0.0022890000000000002,
        "SP95": 0.002099,
        "SP98": 0.002199
      },
      "maj_gouv": {
        "Gazole": "2026-04-23 00:00:00",
        "SP95": "2026-04-15 00:00:00",
        "SP98": "2026-04-15 00:00:00"
      }
    },
    {
      "id": "18200007",
      "lat": 46.722,
      "lon": 2.532,
      "cp": "18200",
      "ville": "Saint-Amand-Montrond",
      "prix": {
        "Gazole": 0.00215,
        "SP95": 0.001999,
        "SP98": 0.0020499999999999997
      },
      "maj_gouv": {
        "Gazole": "2026-04-30 13:00:00",
        "SP95": "2026-04-24 10:02:52",
        "SP98": "2026-04-24 10:02:52"
      }
    },
    {
      "id": "18330001",
      "lat": 47.31545,
      "lon": 2.25574,
      "cp": "18330",
      "ville": "NEUVY-SUR-BARANGEON",
      "prix": {
        "Gazole": 0.0022719999999999997,
        "SP95": 0.002177,
        "SP98": 0.0022400000000000002
      },
      "maj_gouv": {
        "Gazole": "2026-04-27 15:07:20",
        "SP95": "2026-04-27 15:07:20",
        "SP98": "2026-04-27 15:07:20"
      }
    },
    {
      "id": "18220001",
      "lat": 47.195403353380996,
      "lon": 2.5666948514844,
      "cp": "18220",
      "ville": "LES AIX-D'ANGILLON",
      "prix": {
        "Gazole": 0.002219,
        "E85": 0.0008489999999999999,
        "E10": 0.002019,
        "SP98": 0.002139
      },
      "maj_gouv": {
        "Gazole": "2026-04-30 19:38:59",
        "E85": "2026-03-23 10:22:48",
        "E10": "2026-04-30 19:38:59",
        "SP98": "2026-04-30 19:38:59"
      }
    },
    {
      "id": "18570002",
      "lat": 47.063,
      "lon": 2.324,
      "cp": "18570",
      "ville": "La Chapelle-Saint-Ursin",
      "prix": {
        "Gazole": 0.002199,
        "SP95": 0.002089,
        "SP98": 0.002179
      },
      "maj_gouv": {
        "Gazole": "2026-04-29 13:50:59",
        "SP95": "2026-04-29 13:51:00",
        "SP98": "2026-04-29 13:51:00"
      }
    },
    {
      "id": "18700001",
      "lat": 47.475,
      "lon": 2.423,
      "cp": "18700",
      "ville": "Aubigny-sur-Nère",
      "prix": {
        "Gazole": 0.002182,
        "E10": 0.0020139999999999997,
        "SP98": 0.002145
      },
      "maj_gouv": {
        "Gazole": "2026-04-30 09:49:06",
        "E10": "2026-04-30 09:49:06",
        "SP98": "2026-04-30 09:49:07"
      }
    },
    {
      "id": "18230004",
      "lat": 47.121,
      "lon": 2.37,
      "cp": "18230",
      "ville": "Saint-Doulchard",
      "prix": {
        "Gazole": 0.002177,
        "E10": 0.001982,
        "SP98": 0.002068
      },
      "maj_gouv": {
        "Gazole": "2026-04-30 07:17:55",
        "E10": "2026-04-30 07:17:55",
        "SP98": "2026-04-30 07:17:55"
      }
    },
    {
      "id": "18000019",
      "lat": 47.082,
      "lon": 2.384,
      "cp": "18000",
      "ville": "BOURGES",
      "prix": {
        "Gazole": 0.00209,
        "E10": 0.00199
      },
      "maj_gouv": {
        "Gazole": "2026-05-02 00:01:00",
        "E10": "2026-05-02 00:01:00"
      }
    },
    {
      "id": "18400004",
      "lat": 46.996,
      "lon": 2.249,
      "cp": "18400",
      "ville": "SAINT-FLORENT-SUR-CHER",
      "prix": {
        "Gazole": 0.002179,
        "SP95": 0.002049,
        "SP98": 0.002069
      },
      "maj_gouv": {
        "Gazole": "2026-04-29 08:52:22",
        "SP95": "2026-04-29 08:52:22",
        "SP98": "2026-04-29 08:52:22"
      }
    },
    {
      "id": "18300007",
      "lat": 47.334,
      "lon": 2.856,
      "cp": "18300",
      "ville": "ST SATUR",
      "prix": {
        "Gazole": 0.0022,
        "E85": 0.000758,
        "E10": 0.0019890000000000003
      },
      "maj_gouv": {
        "Gazole": "2026-04-29 06:29:32",
        "E85": "2026-04-29 06:29:32",
        "E10": "2026-04-29 06:29:32"
      }
    },
    {
      "id": "18100010",
      "lat": 47.215,
      "lon": 2.109,
      "cp": "18100",
      "ville": "VIERZON",
      "prix": {
        "Gazole": 0.002209,
        "E10": 0.002059,
        "SP98": 0.002179
      },
      "maj_gouv": {
        "Gazole": "2026-05-01 11:29:42",
        "E10": "2026-05-01 11:29:42",
        "SP98": "2026-05-01 11:29:42"
      }
    },
    {
      "id": "18100008",
      "lat": 47.205,
      "lon": 2.072,
      "cp": "18100",
      "ville": "Vierzon",
      "prix": {
        "Gazole": 0.002199,
        "SP95": 0.002049,
        "E85": 0.000819,
        "E10": 0.0019790000000000003
      },
      "maj_gouv": {
        "Gazole": "2026-04-28 08:00:00",
        "SP95": "2026-04-28 08:00:00",
        "E85": "2026-04-15 08:55:44",
        "E10": "2026-04-28 08:00:00"
      }
    },
    {
      "id": "18400001",
      "lat": 47.005,
      "lon": 2.267,
      "cp": "18400",
      "ville": "Saint-Florent-sur-Cher",
      "prix": {
        "Gazole": 0.002179,
        "SP95": 0.002049,
        "E85": 0.000829,
        "SP98": 0.002069
      },
      "maj_gouv": {
        "Gazole": "2026-04-30 07:48:26",
        "SP95": "2026-04-30 07:48:26",
        "E85": "2026-04-30 07:48:26",
        "SP98": "2026-04-30 07:48:26"
      }
    },
    {
      "id": "18390005",
      "lat": 47.097,
      "lon": 2.451,
      "cp": "18390",
      "ville": "Saint-Germain-du-Puy",
      "prix": {
        "Gazole": 0.0024100000000000002,
        "SP95": 0.00219
      },
      "maj_gouv": {
        "Gazole": "2026-04-02 08:17:27",
        "SP95": "2026-04-02 08:17:27"
      }
    },
    {
      "id": "18000022",
      "lat": 47.041867728406004,
      "lon": 2.348930007346,
      "cp": "18000",
      "ville": "Bourges",
      "prix": {
        "Gazole": 0.0022170000000000002,
        "E85": 0.0008179999999999999,
        "E10": 0.002022,
        "SP98": 0.002108
      },
      "maj_gouv": {
        "Gazole": "2026-04-30 08:46:11",
        "E85": "2026-04-30 08:46:12",
        "E10": "2026-04-30 08:46:12",
        "SP98": "2026-04-30 08:46:12"
      }
    },
    {
      "id": "18160002",
      "lat": 46.837,
      "lon": 2.109,
      "cp": "18160",
      "ville": "CHEZAL BENOIT",
      "prix": {
        "Gazole": 0.00225,
        "SP95": 0.00199
      },
      "maj_gouv": {
        "Gazole": "2026-04-17 13:49:34",
        "SP95": "2026-04-17 13:49:34"
      }
    },
    {
      "id": "18500006",
      "lat": 47.095,
      "lon": 2.243,
      "cp": "18500",
      "ville": "MARMAGNE",
      "prix": {
        "Gazole": 0.002549,
        "GPLc": 0.001149,
        "E10": 0.002299,
        "SP98": 0.002399
      },
      "maj_gouv": {
        "Gazole": "2026-05-01 08:00:00",
        "GPLc": "2026-05-01 08:00:00",
        "E10": "2026-05-01 08:00:00",
        "SP98": "2026-05-01 08:00:00"
      }
    }
  ]
}