[
  {
    "id": "39100006",
    "dep": "39",
    "enseigne": "Intermarché",
    "adresse": "",
    "cp": "39100",
    "ville": "",
    "latitude": 47.10875,
    "longitude": 5.50677,
    "carburants": {
      "Gazole": {
        "valeur": "1.829",
        "maj": "2026-06-19 08:52:37"
      },
      "SP95": {
        "valeur": "1.849",
        "maj": "2026-06-19 05:57:43"
      },
      "E85": {
        "valeur": "0.809",
        "maj": "2026-06-11 07:34:34"
      },
      "GPLc": {
        "valeur": "1.096",
        "maj": "2026-04-16 06:42:35"
      },
      "E10": {
        "valeur": "1.819",
        "maj": "2026-06-19 08:52:37"
      }
    }
  },
  {
    "id": "39260003",
    "dep": "39",
    "enseigne": "Intermarché",
    "adresse": "",
    "cp": "39260",
    "ville": "",
    "latitude": 46.439,
    "longitude": 5.722,
    "carburants": {
      "Gazole": {
        "valeur": "1.969",
        "maj": "2026-06-17 14:36:54"
      },
      "E10": {
        "valeur": "1.929",
        "maj": "2026-06-17 14:36:54"
      },
      "SP98": {
        "valeur": "1.999",
        "maj": "2026-06-17 14:36:54"
      }
    }
  },
  {
    "id": "39700013",
    "dep": "39",
    "enseigne": "TotalEnergies Access",
    "adresse": "",
    "cp": "39700",
    "ville": "",
    "latitude": 47.116137241037,
    "longitude": 5.5385215038275,
    "carburants": {}
  },
  {
    "id": "39120002",
    "dep": "39",
    "enseigne": "Intermarché",
    "adresse": "",
    "cp": "39120",
    "ville": "",
    "latitude": 46.958,
    "longitude": 5.409,
    "carburants": {
      "Gazole": {
        "valeur": "1.919",
        "maj": "2026-06-17 06:52:09"
      },
      "E10": {
        "valeur": "1.879",
        "maj": "2026-06-17 06:52:09"
      },
      "SP98": {
        "valeur": "1.999",
        "maj": "2026-06-17 06:52:09"
      }
    }
  },
  {
    "id": "39100008",
    "dep": "39",
    "enseigne": "Indépendant sans enseigne",
    "adresse": "",
    "cp": "39100",
    "ville": "",
    "latitude": 47.089,
    "longitude": 5.481,
    "carburants": {
      "Gazole": {
        "valeur": "1.829",
        "maj": "2026-06-19 08:12:52"
      },
      "SP95": {
        "valeur": "1.849",
        "maj": "2026-06-19 08:12:52"
      },
      "E85": {
        "valeur": "0.809",
        "maj": "2026-06-16 07:26:13"
      },
      "E10": {
        "valeur": "1.819",
        "maj": "2026-06-19 08:12:52"
      }
    }
  },
  {
    "id": "39570009",
    "dep": "39",
    "enseigne": "Carrefour Market",
    "adresse": "",
    "cp": "39570",
    "ville": "",
    "latitude": 46.672167699999996,
    "longitude": 5.5787266,
    "carburants": {
      "Gazole": {
        "valeur": "1.859",
        "maj": "2026-06-18 08:24:31"
      },
      "SP95": {
        "valeur": "1.899",
        "maj": "2026-06-18 08:24:31"
      },
      "E10": {
        "valeur": "1.889",
        "maj": "2026-06-18 08:24:31"
      }
    }
  },
  {
    "id": "39230004",
    "dep": "39",
    "enseigne": "15 rue de la bresse",
    "adresse": "",
    "cp": "39230",
    "ville": "",
    "latitude": 46.846,
    "longitude": 5.477,
    "carburants": {
      "Gazole": {
        "valeur": "2.098",
        "maj": "2026-06-05 12:45:37"
      },
      "SP95": {
        "valeur": "2.096",
        "maj": "2026-06-05 12:45:37"
      },
      "SP98": {
        "valeur": "2.173",
        "maj": "2026-06-05 12:45:37"
      }
    }
  },
  {
    "id": "39100011",
    "dep": "39",
    "enseigne": "Netto",
    "adresse": "",
    "cp": "39100",
    "ville": "",
    "latitude": 47.080169000000005,
    "longitude": 5.4622,
    "carburants": {
      "Gazole": {
        "valeur": "2.012",
        "maj": "2026-06-05 16:16:48"
      },
      "E10": {
        "valeur": "1.899",
        "maj": "2026-06-05 16:16:48"
      }
    }
  },
  {
    "id": "39210001",
    "dep": "39",
    "enseigne": "Avia",
    "adresse": "",
    "cp": "39210",
    "ville": "",
    "latitude": 46.757,
    "longitude": 5.614,
    "carburants": {
      "Gazole": {
        "valeur": "2.029",
        "maj": "2026-06-18 00:01:00"
      },
      "E10": {
        "valeur": "2.029",
        "maj": "2026-06-18 00:01:00"
      },
      "SP98": {
        "valeur": "2.069",
        "maj": "2026-06-18 00:01:00"
      }
    }
  },
  {
    "id": "39700014",
    "dep": "39",
    "enseigne": "TotalEnergies",
    "adresse": "",
    "cp": "39700",
    "ville": "",
    "latitude": 47.151,
    "longitude": 5.727,
    "carburants": {
      "Gazole": {
        "valeur": "1.941",
        "maj": "2026-06-20 06:02:59"
      },
      "SP95": {
        "valeur": "1.970",
        "maj": "2026-06-20 06:03:00"
      },
      "SP98": {
        "valeur": "1.990",
        "maj": "2026-06-20 06:03:00"
      }
    }
  },
  {
    "id": "39210003",
    "dep": "39",
    "enseigne": "TotalEnergies",
    "adresse": "",
    "cp": "39210",
    "ville": "",
    "latitude": 46.763,
    "longitude": 5.599,
    "carburants": {}
  },
  {
    "id": "39460001",
    "dep": "39",
    "enseigne": "Avia",
    "adresse": "",
    "cp": "39460",
    "ville": "",
    "latitude": 46.658,
    "longitude": 6.074,
    "carburants": {
      "Gazole": {
        "valeur": "1.969",
        "maj": "2026-06-19 10:35:19"
      },
      "E85": {
        "valeur": "0.899",
        "maj": "2026-06-19 10:35:19"
      },
      "E10": {
        "valeur": "1.999",
        "maj": "2026-06-19 10:35:19"
      },
      "SP98": {
        "valeur": "2.099",
        "maj": "2026-06-19 10:35:19"
      }
    }
  },
  {
    "id": "39230001",
    "dep": "39",
    "enseigne": "Maximarché",
    "adresse": "",
    "cp": "39230",
    "ville": "",
    "latitude": 46.828,
    "longitude": 5.568,
    "carburants": {
      "Gazole": {
        "valeur": "2.099",
        "maj": "2026-06-04 08:13:39"
      },
      "SP95": {
        "valeur": "2.099",
        "maj": "2026-06-04 08:13:39"
      },
      "SP98": {
        "valeur": "2.179",
        "maj": "2026-06-04 08:13:39"
      }
    }
  },
  {
    "id": "39500007",
    "dep": "39",
    "enseigne": "Shell",
    "adresse": "",
    "cp": "39500",
    "ville": "",
    "latitude": 47.048889,
    "longitude": 5.429444,
    "carburants": {
      "Gazole": {
        "valeur": "2.144",
        "maj": "2026-06-20 00:00:00"
      }
    }
  },
  {
    "id": "39100005",
    "dep": "39",
    "enseigne": "Carrefour",
    "adresse": "",
    "cp": "39100",
    "ville": "",
    "latitude": 47.064,
    "longitude": 5.455,
    "carburants": {
      "Gazole": {
        "valeur": "1.840",
        "maj": "2026-06-19 10:38:18"
      },
      "GPLc": {
        "valeur": "1.097",
        "maj": "2026-04-29 10:25:01"
      },
      "E10": {
        "valeur": "1.830",
        "maj": "2026-06-19 10:38:18"
      },
      "SP98": {
        "valeur": "1.971",
        "maj": "2026-06-19 10:38:18"
      }
    }
  },
  {
    "id": "39402001",
    "dep": "39",
    "enseigne": "Avia",
    "adresse": "",
    "cp": "39400",
    "ville": "",
    "latitude": 46.52443,
    "longitude": 6.02145,
    "carburants": {
      "Gazole": {
        "valeur": "2.030",
        "maj": "2026-06-19 07:46:37"
      },
      "SP95": {
        "valeur": "2.030",
        "maj": "2026-06-19 07:46:37"
      },
      "SP98": {
        "valeur": "2.090",
        "maj": "2026-06-18 09:29:01"
      }
    }
  },
  {
    "id": "39300004",
    "dep": "39",
    "enseigne": "Netto",
    "adresse": "",
    "cp": "39300",
    "ville": "",
    "latitude": 46.74,
    "longitude": 5.916,
    "carburants": {
      "Gazole": {
        "valeur": "1.917",
        "maj": "2026-06-19 12:37:53"
      },
      "E85": {
        "valeur": "0.888",
        "maj": "2026-06-11 13:02:20"
      },
      "E10": {
        "valeur": "1.937",
        "maj": "2026-06-19 12:37:53"
      },
      "SP98": {
        "valeur": "2.052",
        "maj": "2026-06-19 09:20:22"
      }
    }
  },
  {
    "id": "39500001",
    "dep": "39",
    "enseigne": "Système U",
    "adresse": "",
    "cp": "39500",
    "ville": "",
    "latitude": 47.04162,
    "longitude": 5.41781,
    "carburants": {
      "Gazole": {
        "valeur": "1.950",
        "maj": "2026-06-19 08:49:35"
      },
      "E85": {
        "valeur": "0.798",
        "maj": "2026-05-18 10:36:01"
      },
      "E10": {
        "valeur": "1.918",
        "maj": "2026-06-16 08:52:05"
      },
      "SP98": {
        "valeur": "2.018",
        "maj": "2026-06-11 09:16:52"
      }
    }
  },
  {
    "id": "39220002",
    "dep": "39",
    "enseigne": "Avia",
    "adresse": "",
    "cp": "39220",
    "ville": "",
    "latitude": 46.53,
    "longitude": 6.135,
    "carburants": {
      "Gazole": {
        "valeur": "1.999",
        "maj": "2026-06-18 00:01:00"
      },
      "E10": {
        "valeur": "2.009",
        "maj": "2026-06-18 00:01:00"
      },
      "SP98": {
        "valeur": "2.069",
        "maj": "2026-06-18 00:01:00"
      }
    }
  },
  {
    "id": "39400003",
    "dep": "39",
    "enseigne": "Avia",
    "adresse": "",
    "cp": "39400",
    "ville": "",
    "latitude": 46.549,
    "longitude": 6.016,
    "carburants": {
      "Gazole": {
        "valeur": "1.999",
        "maj": "2026-06-18 00:01:00"
      },
      "SP95": {
        "valeur": "2.009",
        "maj": "2026-06-18 00:01:00"
      },
      "SP98": {
        "valeur": "2.069",
        "maj": "2026-06-18 00:01:00"
      }
    }
  },
  {
    "id": "39100010",
    "dep": "39",
    "enseigne": "Avia",
    "adresse": "",
    "cp": "39100",
    "ville": "",
    "latitude": 47.098,
    "longitude": 5.5,
    "carburants": {
      "Gazole": {
        "valeur": "1.948",
        "maj": "2026-06-20 00:00:00"
      },
      "SP95": {
        "valeur": "2.099",
        "maj": "2026-06-03 00:00:00"
      },
      "E85": {
        "valeur": "0.849",
        "maj": "2026-04-15 00:00:00"
      }
    }
  },
  {
    "id": "39000004",
    "dep": "39",
    "enseigne": "Avia",
    "adresse": "",
    "cp": "39000",
    "ville": "",
    "latitude": 46.67,
    "longitude": 5.571,
    "carburants": {
      "Gazole": {
        "valeur": "1.999",
        "maj": "2026-06-18 00:01:00"
      },
      "SP95": {
        "valeur": "2.029",
        "maj": "2026-06-18 00:01:00"
      },
      "SP98": {
        "valeur": "2.069",
        "maj": "2026-06-18 00:01:00"
      }
    }
  },
  {
    "id": "39130004",
    "dep": "39",
    "enseigne": "Elan",
    "adresse": "",
    "cp": "39130",
    "ville": "",
    "latitude": 46.5769840204,
    "longitude": 5.74694452849,
    "carburants": {
      "Gazole": {
        "valeur": "2.090",
        "maj": "2026-06-18 08:00:00"
      },
      "SP95": {
        "valeur": "1.990",
        "maj": "2026-06-18 08:00:00"
      }
    }
  },
  {
    "id": "39200005",
    "dep": "39",
    "enseigne": "Intermarché",
    "adresse": "",
    "cp": "39200",
    "ville": "",
    "latitude": 46.38038,
    "longitude": 5.83492,
    "carburants": {
      "Gazole": {
        "valeur": "1.825",
        "maj": "2026-06-19 08:38:22"
      },
      "SP95": {
        "valeur": "1.890",
        "maj": "2026-06-19 08:38:23"
      },
      "E10": {
        "valeur": "1.850",
        "maj": "2026-06-19 08:38:23"
      }
    }
  },
  {
    "id": "39300001",
    "dep": "39",
    "enseigne": "Système U",
    "adresse": "",
    "cp": "39300",
    "ville": "",
    "latitude": 46.749,
    "longitude": 5.907,
    "carburants": {
      "Gazole": {
        "valeur": "1.939",
        "maj": "2026-06-18 12:29:02"
      },
      "GPLc": {
        "valeur": "1.099",
        "maj": "2026-04-16 11:46:12"
      },
      "E10": {
        "valeur": "1.959",
        "maj": "2026-06-18 12:29:03"
      },
      "SP98": {
        "valeur": "2.059",
        "maj": "2026-06-18 12:29:03"
      }
    }
  },
  {
    "id": "39400002",
    "dep": "39",
    "enseigne": "Intermarché",
    "adresse": "",
    "cp": "39220",
    "ville": "",
    "latitude": 46.501,
    "longitude": 6.028,
    "carburants": {
      "Gazole": {
        "valeur": "1.939",
        "maj": "2026-06-16 15:33:05"
      },
      "E85": {
        "valeur": "0.809",
        "maj": "2026-06-16 15:33:05"
      },
      "E10": {
        "valeur": "1.909",
        "maj": "2026-06-16 15:33:05"
      },
      "SP98": {
        "valeur": "2.019",
        "maj": "2026-06-16 15:33:06"
      }
    }
  },
  {
    "id": "39140001",
    "dep": "39",
    "enseigne": "TotalEnergies",
    "adresse": "",
    "cp": "39140",
    "ville": "",
    "latitude": 46.746,
    "longitude": 5.457,
    "carburants": {
      "Gazole": {
        "valeur": "1.944",
        "maj": "2026-06-18 07:20:48"
      },
      "E10": {
        "valeur": "1.965",
        "maj": "2026-06-18 07:20:48"
      },
      "SP98": {
        "valeur": "1.990",
        "maj": "2026-06-18 07:20:48"
      }
    }
  },
  {
    "id": "39600002",
    "dep": "39",
    "enseigne": "Système U",
    "adresse": "",
    "cp": "39600",
    "ville": "",
    "latitude": 46.915,
    "longitude": 5.757,
    "carburants": {
      "Gazole": {
        "valeur": "1.999",
        "maj": "2026-06-17 09:24:11"
      },
      "E85": {
        "valeur": "0.799",
        "maj": "2026-06-17 09:24:11"
      },
      "E10": {
        "valeur": "1.939",
        "maj": "2026-06-17 09:24:11"
      },
      "SP98": {
        "valeur": "2.079",
        "maj": "2026-06-17 09:24:11"
      }
    }
  },
  {
    "id": "39300006",
    "dep": "39",
    "enseigne": "Leclerc",
    "adresse": "",
    "cp": "39300",
    "ville": "",
    "latitude": 46.746,
    "longitude": 5.92,
    "carburants": {
      "Gazole": {
        "valeur": "1.927",
        "maj": "2026-06-20 01:16:00"
      },
      "SP95": {
        "valeur": "2.112",
        "maj": "2026-06-20 01:16:00"
      },
      "E10": {
        "valeur": "1.943",
        "maj": "2026-06-20 01:16:00"
      }
    }
  },
  {
    "id": "39220006",
    "dep": "39",
    "enseigne": "Intermarché",
    "adresse": "",
    "cp": "39220",
    "ville": "",
    "latitude": 46.486,
    "longitude": 6.055,
    "carburants": {
      "Gazole": {
        "valeur": "1.939",
        "maj": "2026-06-17 09:36:59"
      },
      "E85": {
        "valeur": "0.809",
        "maj": "2026-06-15 07:01:01"
      },
      "E10": {
        "valeur": "1.909",
        "maj": "2026-06-17 09:36:59"
      },
      "SP98": {
        "valeur": "2.019",
        "maj": "2026-06-17 09:36:59"
      }
    }
  },
  {
    "id": "35800003",
    "dep": "39",
    "enseigne": "Intermarché",
    "adresse": "",
    "cp": "39800",
    "ville": "",
    "latitude": 46.839,
    "longitude": 5.687,
    "carburants": {
      "Gazole": {
        "valeur": "1.947",
        "maj": "2026-06-19 09:29:34"
      },
      "E10": {
        "valeur": "1.919",
        "maj": "2026-06-19 09:29:35"
      },
      "SP98": {
        "valeur": "2.042",
        "maj": "2026-06-19 09:29:35"
      }
    }
  },
  {
    "id": "39100013",
    "dep": "39",
    "enseigne": "Netto",
    "adresse": "",
    "cp": "39100",
    "ville": "",
    "latitude": 47.097241,
    "longitude": 5.50206,
    "carburants": {
      "Gazole": {
        "valeur": "1.892",
        "maj": "2026-06-19 05:57:00"
      },
      "E10": {
        "valeur": "1.855",
        "maj": "2026-06-19 05:57:01"
      },
      "SP98": {
        "valeur": "1.971",
        "maj": "2026-06-19 05:57:01"
      }
    }
  },
  {
    "id": "39410002",
    "dep": "39",
    "enseigne": "Intermarché Contact",
    "adresse": "",
    "cp": "39410",
    "ville": "",
    "latitude": 47.02503,
    "longitude": 5.338101999999999,
    "carburants": {
      "Gazole": {
        "valeur": "1.969",
        "maj": "2026-06-12 12:27:58"
      },
      "E10": {
        "valeur": "1.899",
        "maj": "2026-06-12 12:27:58"
      },
      "SP98": {
        "valeur": "2.029",
        "maj": "2026-06-12 12:27:59"
      }
    }
  },
  {
    "id": "39500010",
    "dep": "39",
    "enseigne": "Netto",
    "adresse": "",
    "cp": "39500",
    "ville": "",
    "latitude": 47.04522,
    "longitude": 5.421996999999999,
    "carburants": {
      "Gazole": {
        "valeur": "1.865",
        "maj": "2026-06-19 10:56:14"
      },
      "E85": {
        "valeur": "0.809",
        "maj": "2026-06-17 17:10:51"
      },
      "E10": {
        "valeur": "1.909",
        "maj": "2026-06-19 10:56:15"
      },
      "SP98": {
        "valeur": "2.019",
        "maj": "2026-06-10 15:44:46"
      }
    }
  },
  {
    "id": "39700018",
    "dep": "39",
    "enseigne": "Intermarché Contact",
    "adresse": "",
    "cp": "39700",
    "ville": "",
    "latitude": 47.152,
    "longitude": 5.76,
    "carburants": {
      "Gazole": {
        "valeur": "1.923",
        "maj": "2026-06-17 08:38:59"
      },
      "E10": {
        "valeur": "1.900",
        "maj": "2026-06-12 06:42:38"
      },
      "SP98": {
        "valeur": "1.999",
        "maj": "2026-06-12 06:42:38"
      }
    }
  },
  {
    "id": "39800004",
    "dep": "39",
    "enseigne": "Netto",
    "adresse": "",
    "cp": "39800",
    "ville": "",
    "latitude": 46.847052999999995,
    "longitude": 5.698015,
    "carburants": {
      "Gazole": {
        "valeur": "1.947",
        "maj": "2026-06-19 09:30:57"
      },
      "E10": {
        "valeur": "1.919",
        "maj": "2026-06-19 09:30:57"
      },
      "SP98": {
        "valeur": "2.042",
        "maj": "2026-06-19 09:30:57"
      }
    }
  },
  {
    "id": "39150002",
    "dep": "39",
    "enseigne": "Avia",
    "adresse": "",
    "cp": "39150",
    "ville": "",
    "latitude": 46.58,
    "longitude": 5.954,
    "carburants": {
      "Gazole": {
        "valeur": "2.029",
        "maj": "2026-06-19 08:15:53"
      },
      "SP95": {
        "valeur": "2.029",
        "maj": "2026-06-19 08:15:53"
      },
      "E85": {
        "valeur": "0.899",
        "maj": "2026-06-19 08:15:53"
      }
    }
  },
  {
    "id": "39140006",
    "dep": "39",
    "enseigne": "ENI",
    "adresse": "",
    "cp": "39140",
    "ville": "",
    "latitude": 46.776,
    "longitude": 5.523,
    "carburants": {
      "Gazole": {
        "valeur": "2.199",
        "maj": "2026-06-20 00:01:00"
      },
      "GPLc": {
        "valeur": "1.149",
        "maj": "2026-06-20 00:01:00"
      },
      "E10": {
        "valeur": "2.169",
        "maj": "2026-06-20 00:01:00"
      },
      "SP98": {
        "valeur": "2.269",
        "maj": "2026-06-20 00:01:00"
      }
    }
  },
  {
    "id": "39100004",
    "dep": "39",
    "enseigne": "Esso Express",
    "adresse": "",
    "cp": "39100",
    "ville": "",
    "latitude": 47.086,
    "longitude": 5.496,
    "carburants": {
      "Gazole": {
        "valeur": "2.033",
        "maj": "2026-06-17 12:20:00"
      },
      "E10": {
        "valeur": "1.962",
        "maj": "2026-06-17 12:20:00"
      },
      "SP98": {
        "valeur": "2.053",
        "maj": "2026-06-17 12:20:00"
      }
    }
  },
  {
    "id": "39000007",
    "dep": "39",
    "enseigne": "TotalEnergies Access",
    "adresse": "",
    "cp": "39000",
    "ville": "",
    "latitude": 46.68,
    "longitude": 5.572,
    "carburants": {
      "Gazole": {
        "valeur": "1.861",
        "maj": "2026-06-20 00:01:00"
      },
      "E85": {
        "valeur": "0.819",
        "maj": "2026-06-20 00:01:00"
      },
      "SP98": {
        "valeur": "1.983",
        "maj": "2026-06-20 00:01:00"
      }
    }
  },
  {
    "id": "39230003",
    "dep": "39",
    "enseigne": "Avia",
    "adresse": "",
    "cp": "39230",
    "ville": "",
    "latitude": 46.826,
    "longitude": 5.574,
    "carburants": {
      "Gazole": {
        "valeur": "1.999",
        "maj": "2026-06-19 23:59:00"
      },
      "SP95": {
        "valeur": "2.099",
        "maj": "2026-06-19 23:59:00"
      },
      "SP98": {
        "valeur": "2.179",
        "maj": "2026-06-19 23:59:00"
      }
    }
  },
  {
    "id": "39700012",
    "dep": "39",
    "enseigne": "TotalEnergies Access",
    "adresse": "",
    "cp": "39700",
    "ville": "",
    "latitude": 47.117,
    "longitude": 5.539,
    "carburants": {
      "Gazole": {
        "valeur": "1.851",
        "maj": "2026-06-20 00:01:00"
      },
      "E85": {
        "valeur": "0.809",
        "maj": "2026-06-20 00:01:00"
      },
      "E10": {
        "valeur": "1.838",
        "maj": "2026-06-20 00:01:00"
      },
      "SP98": {
        "valeur": "1.958",
        "maj": "2026-06-20 00:01:00"
      }
    }
  },
  {
    "id": "39220004",
    "dep": "39",
    "enseigne": "Avia",
    "adresse": "",
    "cp": "39220",
    "ville": "",
    "latitude": 46.47731233759401,
    "longitude": 6.0650331274283005,
    "carburants": {
      "Gazole": {
        "valeur": "2.029",
        "maj": "2026-06-18 14:00:53"
      },
      "SP95": {
        "valeur": "2.029",
        "maj": "2026-06-18 14:01:12"
      },
      "E85": {
        "valeur": "0.899",
        "maj": "2026-06-18 14:01:54"
      },
      "GPLc": {
        "valeur": "1.099",
        "maj": "2026-06-18 14:02:11"
      }
    }
  },
  {
    "id": "39110003",
    "dep": "39",
    "enseigne": "Système U",
    "adresse": "",
    "cp": "39110",
    "ville": "",
    "latitude": 46.92428073,
    "longitude": 5.88581893,
    "carburants": {
      "Gazole": {
        "valeur": "1.976",
        "maj": "2026-06-11 09:23:28"
      },
      "E10": {
        "valeur": "1.860",
        "maj": "2026-06-19 12:18:29"
      },
      "SP98": {
        "valeur": "1.969",
        "maj": "2026-06-19 12:18:30"
      }
    }
  },
  {
    "id": "39220005",
    "dep": "39",
    "enseigne": "Carrefour Market",
    "adresse": "",
    "cp": "39220",
    "ville": "",
    "latitude": 46.478735905036004,
    "longitude": 6.064013480641201,
    "carburants": {
      "Gazole": {
        "valeur": "1.999",
        "maj": "2026-06-16 08:53:46"
      },
      "SP95": {
        "valeur": "1.919",
        "maj": "2026-06-19 17:56:46"
      },
      "SP98": {
        "valeur": "1.999",
        "maj": "2026-06-19 17:56:46"
      }
    }
  },
  {
    "id": "39380002",
    "dep": "39",
    "enseigne": "Avia",
    "adresse": "",
    "cp": "39380",
    "ville": "",
    "latitude": 46.98101,
    "longitude": 5.60756,
    "carburants": {
      "Gazole": {
        "valeur": "2.099",
        "maj": "2026-06-03 08:57:06"
      },
      "SP95": {
        "valeur": "2.099",
        "maj": "2026-06-03 08:57:06"
      },
      "SP98": {
        "valeur": "2.179",
        "maj": "2026-06-03 08:57:07"
      }
    }
  },
  {
    "id": "39600001",
    "dep": "39",
    "enseigne": "Avia",
    "adresse": "",
    "cp": "39600",
    "ville": "",
    "latitude": 46.911,
    "longitude": 5.77,
    "carburants": {
      "Gazole": {
        "valeur": "1.999",
        "maj": "2026-06-18 00:01:00"
      },
      "E85": {
        "valeur": "0.899",
        "maj": "2026-06-18 00:01:00"
      },
      "E10": {
        "valeur": "2.029",
        "maj": "2026-06-18 00:01:00"
      },
      "SP98": {
        "valeur": "2.069",
        "maj": "2026-06-18 00:01:00"
      }
    }
  },
  {
    "id": "39570004",
    "dep": "39",
    "enseigne": "Système U",
    "adresse": "",
    "cp": "39570",
    "ville": "",
    "latitude": 46.67,
    "longitude": 5.526,
    "carburants": {
      "Gazole": {
        "valeur": "1.899",
        "maj": "2026-06-19 08:30:30"
      },
      "E85": {
        "valeur": "0.799",
        "maj": "2026-06-12 10:36:37"
      },
      "GPLc": {
        "valeur": "1.099",
        "maj": "2026-06-12 10:36:37"
      },
      "E10": {
        "valeur": "1.899",
        "maj": "2026-06-19 08:30:31"
      },
      "SP98": {
        "valeur": "1.999",
        "maj": "2026-06-19 08:30:31"
      }
    }
  },
  {
    "id": "39500004",
    "dep": "39",
    "enseigne": "TotalEnergies",
    "adresse": "",
    "cp": "39500",
    "ville": "",
    "latitude": 47.047,
    "longitude": 5.427,
    "carburants": {
      "Gazole": {
        "valeur": "1.926",
        "maj": "2026-06-19 18:49:42"
      },
      "E10": {
        "valeur": "1.895",
        "maj": "2026-06-19 18:49:42"
      },
      "SP98": {
        "valeur": "1.990",
        "maj": "2026-06-12 16:24:11"
      }
    }
  },
  {
    "id": "39130009",
    "dep": "39",
    "enseigne": "Indépendant sans enseigne",
    "adresse": "",
    "cp": "39130",
    "ville": "",
    "latitude": 46.662,
    "longitude": 5.776,
    "carburants": {
      "Gazole": {
        "valeur": "1.959",
        "maj": "2026-06-15 10:07:48"
      },
      "E10": {
        "valeur": "1.890",
        "maj": "2026-06-15 10:07:48"
      }
    }
  },
  {
    "id": "39230002",
    "dep": "39",
    "enseigne": "Avia",
    "adresse": "",
    "cp": "39230",
    "ville": "",
    "latitude": 46.808,
    "longitude": 5.582,
    "carburants": {
      "Gazole": {
        "valeur": "2.099",
        "maj": "2026-06-02 22:45:00"
      },
      "SP95": {
        "valeur": "2.079",
        "maj": "2026-06-02 22:45:00"
      },
      "E85": {
        "valeur": "0.999",
        "maj": "2026-04-14 22:45:00"
      },
      "SP98": {
        "valeur": "2.179",
        "maj": "2026-06-02 22:45:00"
      }
    }
  },
  {
    "id": "39170001",
    "dep": "39",
    "enseigne": "Indépendant sans enseigne",
    "adresse": "",
    "cp": "39170",
    "ville": "",
    "latitude": 46.403,
    "longitude": 5.794,
    "carburants": {
      "Gazole": {
        "valeur": "1.994",
        "maj": "2026-06-10 08:45:00"
      },
      "SP95": {
        "valeur": "1.995",
        "maj": "2026-06-10 08:45:00"
      }
    }
  },
  {
    "id": "39100012",
    "dep": "39",
    "enseigne": "Leclerc",
    "adresse": "",
    "cp": "39100",
    "ville": "",
    "latitude": 47.086,
    "longitude": 5.49,
    "carburants": {
      "Gazole": {
        "valeur": "1.829",
        "maj": "2026-06-19 09:31:23"
      },
      "GPLc": {
        "valeur": "1.096",
        "maj": "2026-04-15 10:00:35"
      },
      "E10": {
        "valeur": "1.819",
        "maj": "2026-06-19 09:31:23"
      },
      "SP98": {
        "valeur": "1.970",
        "maj": "2026-06-19 08:14:47"
      }
    }
  },
  {
    "id": "39130008",
    "dep": "39",
    "enseigne": "Carrefour Express",
    "adresse": "",
    "cp": "39130",
    "ville": "",
    "latitude": 46.575,
    "longitude": 5.751,
    "carburants": {
      "Gazole": {
        "valeur": "1.999",
        "maj": "2026-06-17 11:17:40"
      },
      "SP95": {
        "valeur": "1.999",
        "maj": "2026-06-17 11:17:40"
      },
      "SP98": {
        "valeur": "2.069",
        "maj": "2026-06-17 11:17:40"
      }
    }
  },
  {
    "id": "39160001",
    "dep": "39",
    "enseigne": "Système U",
    "adresse": "",
    "cp": "39160",
    "ville": "",
    "latitude": 46.442,
    "longitude": 5.343,
    "carburants": {
      "Gazole": {
        "valeur": "1.899",
        "maj": "2026-06-19 08:05:19"
      },
      "E10": {
        "valeur": "1.939",
        "maj": "2026-06-16 19:12:35"
      },
      "SP98": {
        "valeur": "2.039",
        "maj": "2026-06-16 19:12:35"
      }
    }
  },
  {
    "id": "39570008",
    "dep": "39",
    "enseigne": "Bricomarché",
    "adresse": "",
    "cp": "39570",
    "ville": "",
    "latitude": 46.676,
    "longitude": 5.524,
    "carburants": {
      "Gazole": {
        "valeur": "1.899",
        "maj": "2026-06-19 09:32:03"
      },
      "E85": {
        "valeur": "0.809",
        "maj": "2026-06-12 11:59:28"
      },
      "GPLc": {
        "valeur": "1.099",
        "maj": "2026-05-07 16:49:55"
      },
      "E10": {
        "valeur": "1.899",
        "maj": "2026-06-19 09:32:03"
      },
      "SP98": {
        "valeur": "1.999",
        "maj": "2026-06-19 09:32:03"
      }
    }
  },
  {
    "id": "39170002",
    "dep": "39",
    "enseigne": "Avia",
    "adresse": "",
    "cp": "39170",
    "ville": "",
    "latitude": 46.381,
    "longitude": 5.778,
    "carburants": {
      "Gazole": {
        "valeur": "1.999",
        "maj": "2026-06-18 00:01:00"
      },
      "SP95": {
        "valeur": "2.029",
        "maj": "2026-06-18 00:01:00"
      },
      "SP98": {
        "valeur": "2.069",
        "maj": "2026-06-18 00:01:00"
      }
    }
  },
  {
    "id": "39270001",
    "dep": "39",
    "enseigne": "Avia",
    "adresse": "",
    "cp": "39270",
    "ville": "",
    "latitude": 46.521,
    "longitude": 5.61,
    "carburants": {
      "Gazole": {
        "valeur": "1.999",
        "maj": "2026-06-17 18:58:45"
      },
      "SP95": {
        "valeur": "2.029",
        "maj": "2026-06-17 18:58:45"
      },
      "E85": {
        "valeur": "0.899",
        "maj": "2026-04-27 19:06:03"
      }
    }
  },
  {
    "id": "39240001",
    "dep": "39",
    "enseigne": "Système U",
    "adresse": "",
    "cp": "39240",
    "ville": "",
    "latitude": 46.394,
    "longitude": 5.57,
    "carburants": {
      "Gazole": {
        "valeur": "1.969",
        "maj": "2026-06-18 16:37:42"
      },
      "E10": {
        "valeur": "1.959",
        "maj": "2026-06-18 16:37:42"
      },
      "SP98": {
        "valeur": "1.999",
        "maj": "2026-06-18 16:37:42"
      }
    }
  },
  {
    "id": "39380001",
    "dep": "39",
    "enseigne": "Système U",
    "adresse": "",
    "cp": "39380",
    "ville": "",
    "latitude": 46.982,
    "longitude": 5.582,
    "carburants": {
      "Gazole": {
        "valeur": "1.895",
        "maj": "2026-06-19 12:09:34"
      },
      "E10": {
        "valeur": "1.905",
        "maj": "2026-06-19 12:09:35"
      },
      "SP98": {
        "valeur": "2.015",
        "maj": "2026-06-19 12:09:35"
      }
    }
  },
  {
    "id": "39500006",
    "dep": "39",
    "enseigne": "Intermarché Contact",
    "adresse": "",
    "cp": "39500",
    "ville": "",
    "latitude": 47.07224,
    "longitude": 5.41392,
    "carburants": {
      "Gazole": {
        "valeur": "1.999",
        "maj": "2026-06-11 13:37:24"
      },
      "E85": {
        "valeur": "0.809",
        "maj": "2026-06-18 09:22:32"
      },
      "E10": {
        "valeur": "1.929",
        "maj": "2026-06-03 11:11:57"
      },
      "SP98": {
        "valeur": "2.049",
        "maj": "2026-06-03 11:11:57"
      }
    }
  },
  {
    "id": "39200003",
    "dep": "39",
    "enseigne": "TotalEnergies Access",
    "adresse": "",
    "cp": "39200",
    "ville": "",
    "latitude": 46.379,
    "longitude": 5.839,
    "carburants": {
      "Gazole": {
        "valeur": "1.822",
        "maj": "2026-06-19 07:15:42"
      },
      "E85": {
        "valeur": "0.839",
        "maj": "2026-06-19 07:15:42"
      },
      "GPLc": {
        "valeur": "1.070",
        "maj": "2026-06-19 07:15:43"
      },
      "E10": {
        "valeur": "1.851",
        "maj": "2026-06-19 07:15:43"
      },
      "SP98": {
        "valeur": "1.981",
        "maj": "2026-06-19 07:15:43"
      }
    }
  },
  {
    "id": "39100003",
    "dep": "39",
    "enseigne": "TotalEnergies",
    "adresse": "",
    "cp": "39100",
    "ville": "",
    "latitude": 47.02,
    "longitude": 5.495,
    "carburants": {
      "Gazole": {
        "valeur": "1.941",
        "maj": "2026-06-19 18:48:30"
      },
      "SP95": {
        "valeur": "1.984",
        "maj": "2026-06-19 18:48:31"
      }
    }
  },
  {
    "id": "39150001",
    "dep": "39",
    "enseigne": "Système U",
    "adresse": "",
    "cp": "39150",
    "ville": "",
    "latitude": 46.572,
    "longitude": 5.956,
    "carburants": {
      "Gazole": {
        "valeur": "1.939",
        "maj": "2026-06-19 15:42:32"
      },
      "GPLc": {
        "valeur": "1.039",
        "maj": "2026-06-04 07:28:44"
      },
      "E10": {
        "valeur": "1.929",
        "maj": "2026-06-19 15:42:32"
      },
      "SP98": {
        "valeur": "2.029",
        "maj": "2026-06-19 15:42:33"
      }
    }
  },
  {
    "id": "39300008",
    "dep": "39",
    "enseigne": "Netto",
    "adresse": "",
    "cp": "39300",
    "ville": "",
    "latitude": 46.748652,
    "longitude": 5.905161,
    "carburants": {
      "Gazole": {
        "valeur": "1.917",
        "maj": "2026-06-19 12:39:08"
      },
      "E10": {
        "valeur": "1.937",
        "maj": "2026-06-19 12:39:09"
      },
      "SP98": {
        "valeur": "2.052",
        "maj": "2026-06-19 09:21:07"
      }
    }
  },
  {
    "id": "39270002",
    "dep": "39",
    "enseigne": "Système U",
    "adresse": "",
    "cp": "39270",
    "ville": "",
    "latitude": 46.533,
    "longitude": 5.605,
    "carburants": {
      "Gazole": {
        "valeur": "1.885",
        "maj": "2026-06-19 10:36:25"
      },
      "E85": {
        "valeur": "0.829",
        "maj": "2026-06-19 10:36:25"
      },
      "E10": {
        "valeur": "1.889",
        "maj": "2026-06-19 10:36:26"
      },
      "SP98": {
        "valeur": "1.999",
        "maj": "2026-06-19 10:36:26"
      }
    }
  },
  {
    "id": "39140003",
    "dep": "39",
    "enseigne": "Système U",
    "adresse": "",
    "cp": "39140",
    "ville": "",
    "latitude": 46.745,
    "longitude": 5.45,
    "carburants": {
      "Gazole": {
        "valeur": "1.860",
        "maj": "2026-06-19 09:05:32"
      },
      "SP95": {
        "valeur": "1.965",
        "maj": "2026-06-19 09:05:32"
      },
      "SP98": {
        "valeur": "1.989",
        "maj": "2026-06-19 09:05:32"
      }
    }
  },
  {
    "id": "39000010",
    "dep": "39",
    "enseigne": "Carrefour",
    "adresse": "",
    "cp": "39000",
    "ville": "",
    "latitude": 46.674094018411004,
    "longitude": 5.5395137771469996,
    "carburants": {
      "Gazole": {
        "valeur": "1.899",
        "maj": "2026-06-19 14:51:02"
      },
      "GPLc": {
        "valeur": "0.999",
        "maj": "2026-06-19 14:51:02"
      },
      "E10": {
        "valeur": "1.899",
        "maj": "2026-06-19 14:51:03"
      },
      "SP98": {
        "valeur": "1.999",
        "maj": "2026-06-19 14:51:03"
      }
    }
  },
  {
    "id": "39130010",
    "dep": "39",
    "enseigne": "TotalEnergies",
    "adresse": "",
    "cp": "39130",
    "ville": "",
    "latitude": 46.577049585039,
    "longitude": 5.7537848437034,
    "carburants": {
      "Gazole": {
        "valeur": "1.992",
        "maj": "2026-06-19 19:06:40"
      },
      "E10": {
        "valeur": "1.949",
        "maj": "2026-06-19 19:06:40"
      },
      "SP98": {
        "valeur": "1.990",
        "maj": "2026-06-19 19:06:40"
      }
    }
  },
  {
    "id": "39120003",
    "dep": "39",
    "enseigne": "Avia",
    "adresse": "",
    "cp": "39120",
    "ville": "",
    "latitude": 46.971070999999995,
    "longitude": 5.397918000000001,
    "carburants": {
      "Gazole": {
        "valeur": "1.999",
        "maj": "2026-06-19 18:00:00"
      },
      "SP95": {
        "valeur": "2.079",
        "maj": "2026-06-19 18:00:00"
      },
      "SP98": {
        "valeur": "2.179",
        "maj": "2026-06-19 18:00:00"
      }
    }
  },
  {
    "id": "39200002",
    "dep": "39",
    "enseigne": "Avia",
    "adresse": "",
    "cp": "39200",
    "ville": "",
    "latitude": 46.38322076,
    "longitude": 5.861767489999999,
    "carburants": {}
  },
  {
    "id": "39700015",
    "dep": "39",
    "enseigne": "Avia",
    "adresse": "",
    "cp": "39700",
    "ville": "",
    "latitude": 47.146967000000004,
    "longitude": 5.579313000000001,
    "carburants": {
      "Gazole": {
        "valeur": "2.071",
        "maj": "2026-06-19 06:00:00"
      },
      "GPLc": {
        "valeur": "1.188",
        "maj": "2026-06-19 06:00:00"
      },
      "E10": {
        "valeur": "2.026",
        "maj": "2026-06-19 06:00:00"
      },
      "SP98": {
        "valeur": "2.110",
        "maj": "2026-06-19 06:00:00"
      }
    }
  },
  {
    "id": "39190007",
    "dep": "39",
    "enseigne": "TotalEnergies",
    "adresse": "",
    "cp": "39190",
    "ville": "",
    "latitude": 46.57352,
    "longitude": 5.434063,
    "carburants": {
      "Gazole": {
        "valeur": "1.964",
        "maj": "2026-06-19 21:21:38"
      },
      "E85": {
        "valeur": "0.869",
        "maj": "2026-06-13 07:09:36"
      },
      "E10": {
        "valeur": "1.968",
        "maj": "2026-06-19 21:21:38"
      },
      "SP98": {
        "valeur": "1.990",
        "maj": "2026-06-13 07:09:36"
      }
    }
  },
  {
    "id": "39700017",
    "dep": "39",
    "enseigne": "Avia",
    "adresse": "",
    "cp": "39700",
    "ville": "",
    "latitude": 47.149047,
    "longitude": 5.583634,
    "carburants": {
      "Gazole": {
        "valeur": "2.071",
        "maj": "2026-06-17 07:00:38"
      },
      "GPLc": {
        "valeur": "1.188",
        "maj": "2026-06-17 07:00:38"
      },
      "E10": {
        "valeur": "2.026",
        "maj": "2026-06-17 07:00:38"
      },
      "SP98": {
        "valeur": "2.110",
        "maj": "2026-06-17 07:00:38"
      }
    }
  },
  {
    "id": "39570010",
    "dep": "39",
    "enseigne": "TotalEnergies Contact",
    "adresse": "",
    "cp": "39570",
    "ville": "",
    "latitude": 46.669,
    "longitude": 5.576,
    "carburants": {
      "Gazole": {
        "valeur": "1.921",
        "maj": "2026-06-19 08:31:33"
      },
      "E10": {
        "valeur": "1.983",
        "maj": "2026-06-19 08:31:33"
      },
      "SP98": {
        "valeur": "1.990",
        "maj": "2026-06-19 08:31:33"
      }
    }
  },
  {
    "id": "39200007",
    "dep": "39",
    "enseigne": "Avia",
    "adresse": "",
    "cp": "39200",
    "ville": "",
    "latitude": 46.383,
    "longitude": 5.862,
    "carburants": {
      "Gazole": {
        "valeur": "2.029",
        "maj": "2026-06-18 08:12:07"
      },
      "SP95": {
        "valeur": "2.029",
        "maj": "2026-06-18 08:12:07"
      },
      "SP98": {
        "valeur": "2.069",
        "maj": "2026-06-18 08:12:07"
      }
    }
  },
  {
    "id": "39110007",
    "dep": "39",
    "enseigne": "TotalEnergies Access",
    "adresse": "",
    "cp": "39110",
    "ville": "",
    "latitude": 46.949,
    "longitude": 5.874,
    "carburants": {
      "Gazole": {
        "valeur": "1.827",
        "maj": "2026-06-20 00:01:00"
      },
      "E85": {
        "valeur": "0.859",
        "maj": "2026-06-20 00:01:00"
      },
      "E10": {
        "valeur": "1.842",
        "maj": "2026-06-20 00:01:00"
      },
      "SP98": {
        "valeur": "1.962",
        "maj": "2026-06-20 00:01:00"
      }
    }
  }
]